{
  "Title": "2 Base Carrier (Khala) (vs. Terran)",
  "Link": "https://www.youtube.com/watch?v=163qudecaz4",
  "secondsDelayed": -5,
  "buildSteps":[
    {"text":"4 probe (5) and split probes",                                                                                                                           "time":"0:05"},
    {"text":"5 probe (6)",                                                                                                                                            "time":"0:15"},
    {"text":"6 probe (7)",                                                                                                                                            "time":"0:28"},
    {"text":"7 probe (8)",                                                                                                                                            "time":"0:41"},
    {"text":"8 pylon",                                                                                                                                                "time":"0:48"},
    {"text":"8 probe (9)",                                                                                                                                            "time":"0:54"},
    {"text":"9 probe (10)",                                                                                                                                           "time":"1:11"},
    {"text":"10 gateway",                                                                                                                                             "time":"1:14"},
    {"text":"10 probe (11)",                                                                                                                                          "time":"1:23"},
    {"text":"11 gas",                                                                                                                                                 "time":"1:32"},
    {"text":"11 probe (12)",                                                                                                                                          "time":"1:36"},
    {"text":"12 probe (13) and send a scout vertically on circuit breakers",                                                                                          "time":"1:49"},
    {"text":"13 core",                                                                                                                                                "time":"1:55"},
    {"text":"13 probe (14) and send 3 probes to gas",                                                                                                                 "time":"2:01"},
    {"text":"14 pylon (block outer minerals with this one)",                                                                                                          "time":"2:12"},
    {"text":"14 probe (15)",                                                                                                                                          "time":"2:14"},
    {"text":"15 probe (16)",                                                                                                                                          "time":"2:26"},
    {"text":"16 1st dragoon",                                                                                                                                         "time":"2:37"},
    {"text":"18 probe (17)",                                                                                                                                          "time":"2:38"},
    {"text":"19 research goon range",                                                                                                                                 "time":"2:46"},
    {"text":"19 probe (18)",                                                                                                                                          "time":"2:52"},
    {"text":"20 probe (19)",                                                                                                                                          "time":"3:04"},
    {"text":"21 2nd dragoon and scout with 1st dragoon and send the next probe to natural",                                                                           "time":"3:08"},
    {"text":"23 nexus",                                                                                                                                               "time":"3:34"},
    {"text":"23 pylon at natural to make wallin",                                                                                                                     "time":"3:40"},
    {"text":"23 probe (20), 1st dragoon at enemy natural, 2nd dragoon stays back (scouting probe dies)",                                                              "time":"3:45"},
    {"text":"23 3rd dragoon",                                                                                                                                         "time":"3:54"},
    {"text":"25 probe (20)",                                                                                                                                          "time":"4:02"},
    {"text":"26 robotics",                                                                                                                                            "time":"4:11"},
    {"text":"26 probe (21)",                                                                                                                                          "time":"4:14"},
    {"text":"27 4th dragoon and rally goons to enemy natural if 1st vulture is dead",                                                                                 "time":"4:25"},
    {"text":"29 probe (22)",                                                                                                                                          "time":"4:26"},
    {"text":"30 probe (23) and peak in with goon to check if he has natural",                                                                                         "time":"4:38"},
    {"text":"31 send 9 probes to natural minerals",                                                                                                                   "time":"4:46"},
    {"text":"31 probe at main (24)",                                                                                                                                  "time":"4:50"},
    {"text":"32 probe at natural (25)",                                                                                                                               "time":"4:54"},
    {"text":"33 2nd gateway and 5th dragoon",                                                                                                                         "time":"4:57"},
    {"text":"35 observatory",                                                                                                                                         "time":"5:03"},
    {"text":"35 probe at main (26)",                                                                                                                                  "time":"5:08"},
    {"text":"36 probe at natural (27)",                                                                                                                               "time":"5:08"},
    {"text":"37 pylon",                                                                                                                                               "time":"5:12"},
    {"text":"37 probe at main (28)",                                                                                                                                  "time":"5:20"},
    {"text":"38 probe at natural (29)",                                                                                                                               "time":"5:20"},
    {"text":"39 gas at natural and defend main with dragoons if enemy is not coming out",                                                                             "time":"5:23"},
    {"text":"39 1st observer",                                                                                                                                        "time":"5:31"},
    {"text":"40 6th dragoon",                                                                                                                                         "time":"5:33"},
    {"text":"42 1st stargate",                                                                                                                                        "time":"5:35"},
    {"text":"42 probe at main (30)",                                                                                                                                  "time":"5:38"},
    {"text":"43 probe at natural (31)",                                                                                                                               "time":"5:38"},
    {"text":"44 7th dragoon",                                                                                                                                         "time":"5:44"},
    {"text":"46 pylon at natural to make wallin",                                                                                                                     "time":"5:48"},
    {"text":"46 probe at main (32)",                                                                                                                                  "time":"5:53"},
    {"text":"47 probe at natural (33)",                                                                                                                               "time":"5:53"},
    {"text":"48 2nd observer and send the 1st to scout and send 3 probes to natural gas",                                                                             "time":"5:57"},
    {"text":"49 pylon to intercept dropship",                                                                                                                         "time":"6:12"},
    {"text":"49 probe at main (34)",                                                                                                                                  "time":"6:14"},
    {"text":"50 probe at natural (35)",                                                                                                                               "time":"6:14"},
    {"text":"51 make 2 dragoons and a pylon",                                                                                                                         "time":"6:16"},
    {"text":"55 probe at main (36)",                                                                                                                                  "time":"6:26"},
    {"text":"56 probe at natural (37)",                                                                                                                               "time":"6:26"},
    {"text":"57 2nd stargate",                                                                                                                                        "time":"6:27"},
    {"text":"57 probe at main (38)",                                                                                                                                  "time":"6:38"},
    {"text":"58 probe at natural (39)",                                                                                                                               "time":"6:38"},
    {"text":"59 if enemy if going for 4-5 factories or bio + mech, cancel the stargate and make 5-6 gateways and reavers",                                            "time":"6:42"},
    {"text":"59 fleet beacon",                                                                                                                                        "time":"6:44"},
    {"text":"59 probe at main (40)",                                                                                                                                  "time":"6:51"},
    {"text":"60 probe at natural (41)",                                                                                                                               "time":"6:51"},
    {"text":"61 make 2 dragoons",                                                                                                                                     "time":"6:57"},
    {"text":"65 probe at main (42)",                                                                                                                                  "time":"7:04"},
    {"text":"66 probe at natural (43)",                                                                                                                               "time":"7:04"},
    {"text":"67 if you see starport send goons in a defensive position around you base to intercept dropship",                                                        "time":"7:07"},
    {"text":"67 2 pylons",                                                                                                                                            "time":"7:10"},
    {"text":"67 probe at main (44)",                                                                                                                                  "time":"7:17"},
    {"text":"68 probe at natural (45)",                                                                                                                               "time":"7:17"},
    {"text":"69 pylon",                                                                                                                                               "time":"7:31"},
    {"text":"69 make 2 carriers",                                                                                                                                     "time":"7:36"},
    {"text":"81 research interceptor upgrade",                                                                                                                        "time":"7:47"},
    {"text":"81 make 2 dragoons and delay his 3rd",                                                                                                                   "time":"7:49"},
    {"text":"85 probe at main (46)",                                                                                                                                  "time":"7:54"},
    {"text":"86 probe at natural (47)",                                                                                                                               "time":"7:54"},
    {"text":"87 +1 air weapons",                                                                                                                                      "time":"7:55"},
    {"text":"87 if you see 3rd enemy expo you can take your 3rd nexus",                                                                                               "time":"7:57"},
    {"text":"87 3rd expo",                                                                                                                                            "time":"8:06"},
    {"text":"87 probe at main (48)",                                                                                                                                  "time":"8:12"},
    {"text":"88 probe at natural (49)",                                                                                                                               "time":"8:12"},
    {"text":"89 make 2 dragoons",                                                                                                                                     "time":"8:16"},
    {"text":"91 pylon",                                                                                                                                               "time":"8:19"},
    {"text":"91 3rd observer",                                                                                                                                        "time":"8:20"},
    {"text":"92 probe at main (50)",                                                                                                                                  "time":"8:24"},
    {"text":"93 probe at natural (51)",                                                                                                                               "time":"8:24"},
    {"text":"94 pylon at 3rd expo",                                                                                                                                   "time":"8:26"},
    {"text":"94 pylon to block his 4th",                                                                                                                              "time":"8:29"},
    {"text":"94 probe at main (52)",                                                                                                                                  "time":"8:37"},
    {"text":"95 probe at natural (53)",                                                                                                                               "time":"8:37"},
    {"text":"96 2 more gateways",                                                                                                                                     "time":"8:43"},
    {"text":"96 2 more carriers and interceptors for the first 2",                                                                                                    "time":"9:03"},
    {"text":"108 make 2 dragoons",                                                                                                                                    "time":"9:14"},
    {"text":"112 4th observer",                                                                                                                                       "time":"9:21"},
    {"text":"113 2 more gateways",                                                                                                                                    "time":"9:24"},
    {"text":"113 start making rounds of zealots",                                                                                                                     "time":"9:28"},
    {"text":"xxx probe at main (54)",                                                                                                                                 "time":"9:30"},
    {"text":"xxx probe at natural (55)",                                                                                                                              "time":"9:30"},
    {"text":"xxx probe at 3rd expo (56)",                                                                                                                             "time":"8:30"},
    {"text":"xxx send 6 probes from each base to 3rd expo",                                                                                                           "time":"9:35"},
    {"text":"xxx forge",                                                                                                                                              "time":"9:40"},
    {"text":"xxx delay his attack with initial goons to make more ground units",                                                                                      "time":"9:50"},
    {"text":"xxx 2 pylons at 3rd expo",                                                                                                                               "time":"9:52"},
    {"text":"xxx try and defend with 4 carriers and cut off his reinforcements with goons",                                                                           "time":"10:30"},
    {"text":"xxx if you can't cut off his reinforcements, just save the goons and kill the pushing tanks with carriers and kill his 3rd expo after",                  "time":"10:40"},
    {"text":"xxx END OF BUILD ORDER",                                                                                                                                 "time":"10:50"}
  ]
}
