{
  "Title": "10 Forge into +1G 6 30 SpeedLots into midgame (Jaeyun) (vs. Zerg)",
  "Link": "https://www.youtube.com/watch?v=rmt8H0Lftng",
  "secondsDelayed": -5,
  "buildSteps":[
    {"text":"4 probe (5) and split probes",                                                                                       "time":"0:05"},
    {"text":"5 probe (6)",                                                                                                        "time":"0:16"},
    {"text":"6 probe (7)",                                                                                                        "time":"0:29"},
    {"text":"7 75% send a probe to natural",                                                                                      "time":"0:38"},
    {"text":"7 probe (8)",                                                                                                        "time":"0:42"},
    {"text":"8 pylon and send it to scout 1st overlord and return it to natural",                                                 "time":"0:50"},
    {"text":"8 probe (9)",                                                                                                        "time":"0:57"},
    {"text":"9 probe (10)",                                                                                                       "time":"1:12"},
    {"text":"10 forge and send it to scout the other near main if you didn't find 1st overlord",                                  "time":"1:19"},
    {"text":"10 probe (11)",                                                                                                      "time":"1:29"},
    {"text":"11 probe (12)",                                                                                                      "time":"1:41"},
    {"text":"12 probe (13) and send it to natural",                                                                               "time":"1:53"},
    {"text":"13 1st cannon at natural and send the probe to mine natural",                                                        "time":"2:03"},
    {"text":"13 probe (14)",                                                                                                      "time":"2:06"},
    {"text":"14 probe (15)",                                                                                                      "time":"2:19"},
    {"text":"15 nexus and send it to mine natural or block entrance",                                                             "time":"2:31"},
    {"text":"15 probe (16)",                                                                                                      "time":"2:36"},
    {"text":"16 gateway at natural to complete wall",                                                                             "time":"2:49"},
    {"text":"16 pylon at main near nexus",                                                                                        "time":"2:58"},
    {"text":"16 probe (17)",                                                                                                      "time":"3:03"},
    {"text":"17 gas",                                                                                                             "time":"3:08"},
    {"text":"17 probe at main (18)",                                                                                              "time":"3:19"},
    {"text":"18 probe at main (19)",                                                                                              "time":"3:32"},
    {"text":"19 core at main and send 3 probes to gas and send scout to scout the 3rd hatchery",                                  "time":"3:29"},
    {"text":"19 1st zealot",                                                                                                      "time":"3:40"},
    {"text":"21 ~700 health send 4 probes to natural minerals",                                                                   "time":"3:41"},
    {"text":"21 probe at main (20)",                                                                                              "time":"3:47"},
    {"text":"22 probe at natural (21)",                                                                                           "time":"3:53"},
    {"text":"23 probe at main (22)",                                                                                              "time":"4:00"},
    {"text":"23 +1 ground weapons",                                                                                               "time":"4:01"},
    {"text":"24 probe at natural (23)",                                                                                           "time":"4:06"},
    {"text":"25 2nd zealot",                                                                                                      "time":"4:10"},
    {"text":"27 probe at main (24)",                                                                                              "time":"4:12"},
    {"text":"28 citadel",                                                                                                         "time":"4:21"},
    {"text":"28 probe at main (25)",                                                                                              "time":"4:19"},
    {"text":"39 probe at natural (26)",                                                                                           "time":"4:24"},
    {"text":"30 pylon at main for gateways",                                                                                      "time":"4:28"},
    {"text":"30 3rd zealot",                                                                                                      "time":"4:34"},
    {"text":"32 probe at main (27)",                                                                                              "time":"4:35"},
    {"text":"33 probe at natural (28)",                                                                                           "time":"4:36"},
    {"text":"34 gas at natural",                                                                                                  "time":"4:42"},
    {"text":"34 probe at main (29)",                                                                                              "time":"4:50"},
    {"text":"35 probe at natural (30)",                                                                                           "time":"4:51"},
    {"text":"36 2nd gateway",                                                                                                     "time":"4:53"},
    {"text":"36 4th zealot",                                                                                                      "time":"5:00"},
    {"text":"38 research zealot speed",                         								                                                  "time":"5:05"},
    {"text":"38 probe at main (31)",                                                                                              "time":"5:09"},
    {"text":"39 probe at natural (32)",                                                                                           "time":"5:10"},
    {"text":"40 pylon at natural for robotics",                                                                                   "time":"5:13"},
    {"text":"40 pylon at main for gateways",                                                                                      "time":"5:20"},
    {"text":"40 probe at main (33)",                                                                                              "time":"5:21"},
    {"text":"41 probe at natural (34)",                                                                                           "time":"5:22"},
    {"text":"42 templar archives",                                                                                                "time":"5:25"},
    {"text":"42 probe at main (35)",                                                                                              "time":"5:30"},
    {"text":"43 probe at natural (36)",                                                                                           "time":"5:31"},
    {"text":"44 make 2 zealots",                                                                                                  "time":"5:37"},
    {"text":"48 make 2 more gateways",                                                                                            "time":"5:47"},
    {"text":"48 probe at main (37)",                                                                                              "time":"5:56"},
    {"text":"49 probe at natural (38)",                                                                                           "time":"5:57"},
    {"text":"50 make 2 zealots",                                                                                                  "time":"6:01"},
    {"text":"54 pylon at natural for cannons",                                                                                    "time":"6:09"},
    {"text":"54 probe at main (39)",                                                                                              "time":"6:13"},
    {"text":"55 probe at natural (40)",                                                                                           "time":"6:14"},
    {"text":"56 move out with zealots and cannon at main",                                                                        "time":"6:20"},
    {"text":"56 cannon at natural (if mutas make 1 more cannon per base)",                                                        "time":"6:26"},
    {"text":"56 make 4 high templars",                                                                                            "time":"6:32"},
    {"text":"64 2 more gateways",                                                                                                 "time":"6:48"},
    {"text":"64 +1 ground armor",                                                                                                 "time":"6:50"},
    {"text":"64 pylon at main (start blocking a probe if all-in mutas)",                                                          "time":"6:58"},
    {"text":"64 probe at main (41)",                                                                                              "time":"7:00"},
    {"text":"65 probe at natural (42)",                                                                                           "time":"7:01"},
    {"text":"66 pylon for gateways",                                                                                              "time":"7:04"},
    {"text":"66 make 3 high templars (or 2 and stargate)",                                                                        "time":"7:16"},
    {"text":"72 2 pylons at main",                                                                                                "time":"7:20"},
    {"text":"72 research storm",                                                                                                  "time":"7:38"},
    {"text":"72 make 2 zealots",                                                                                                  "time":"7:39"},
    {"text":"76 probe at main (43)",                                                                                              "time":"7:40"},
    {"text":"77 probe at natural (44)",                                                                                           "time":"7:41"},
    {"text":"78 robotics",                                                                                                        "time":"7:58"},
    {"text":"78 make 3 zealots",                                                                                                  "time":"8:02"},
    {"text":"84 pylon at main",                                                                                                   "time":"8:08"},
    {"text":"84 2 more gateways",                                                                                                 "time":"8:14"},
    {"text":"84 research goon range",                                                                                             "time":"8:16"},
    {"text":"84 make high templars and zealots and resume making probes",                                                         "time":"8:20"},
    {"text":"xx pylon at main",                                                                                                   "time":"8:32"},
    {"text":"xx from here make only goons and send probe to take a third",                                                        "time":"8:45"},
    {"text":"xx observatory",                                                                                                     "time":"8:56"},
    {"text":"xx pylon at third",                                                                                                  "time":"9:05"},
    {"text":"xx pylon at third",                                                                                                  "time":"9:28"},
    {"text":"xx 1st observer",                                                                                                    "time":"9:32"},
    {"text":"xx take a third expo and make a cannon there",                                                                       "time":"9:42"},
    {"text":"xx +2 ground armor",                                                                                                 "time":"9:50"},
    {"text":"xx 2nd observer",                                                                                                    "time":"9:57"},
    {"text":"xx cannon at third expo",                                                                                            "time":"10:05"},
    {"text":"END OF BUILD ORDER",                                                                                                 "time":"10:15"}
  ]
}
