{
  "Title": "2 Gate vs Random (Stork) (vs. Zerg)",
  "Link": "https://www.youtube.com/watch?app=desktop&v=nCPMEiaV8rc&feature=youtu.be",
  "secondsDelayed": -5,
  "buildSteps":[
    {"text":"4 probe (5) and split probes",                                                                                       "time":"0:05"},
    {"text":"5 probe (6)",                                                                                                        "time":"0:16"},
    {"text":"6 probe (7)",                                                                                                        "time":"0:29"},
    {"text":"7 probe (8)",                                                                                                        "time":"0:42"},
    {"text":"8 pylon at main near the entrance",                           							                                          "time":"0:50"},
    {"text":"8 probe (9)",                                                                                                        "time":"0:54"},
    {"text":"9 probe (10)",                                                                                                       "time":"1:10"},
    {"text":"10 1st gateway",                                                                                                     "time":"1:18"},
    {"text":"10 probe (11)",                                                                                                      "time":"1:23"},
    {"text":"11 probe (12)",                                                                                                      "time":"1:35"},
    {"text":"12 2nd gateway and scout with probe clockwise on circuit breakers",                                                  "time":"1:44"},
    {"text":"12 probe (13)",                                                                                                      "time":"1:50"},
    {"text":"13 1st zealot (keep it hidden)",                                                                                     "time":"2:00"},
    {"text":"15 probe (14)",                                                                                                      "time":"2:02"},
    {"text":"16 pylon at main",                                                                                                   "time":"2:10"},
    {"text":"16 probe (15)",                                                                                                      "time":"2:15"},
    {"text":"17 make 2 zealots and scout with another probe your natural for overlord",                                           "time":"2:32"},
    {"text":"21 pylon (block outer minerals with this one)",                                                                      "time":"2:36"},
    {"text":"21 probe (16)",                                                                     				                          "time":"2:39"},
    {"text":"22 probe (17)",                                                                     				                          "time":"2:53"},
    {"text":"23 make 2 zealots and attack with the first 3 if enemy is not cross position",               			                  "time":"2:59"},
    {"text":"27 probe (18)",                                                                     				                          "time":"3:05"},
    {"text":"28 probe (19)",                                                                                            				  "time":"3:17"},
    {"text":"29 make 2 zealots and keep rallying them at enemy",     			                                                			  "time":"3:26"},
    {"text":"33 pylon at main",     			                       			  			                                                	  "time":"3:28"},
    {"text":"33 send a probe to natural",                                                                           			  		  "time":"3:46"},
    {"text":"33 nexus",  	                                                                                              				  "time":"3:55"},
    {"text":"33 probe (20)",                                                  			  		                                    	  "time":"4:00"},
    {"text":"34 probe (21)",                                                                                             				  "time":"4:10"},
    {"text":"35 make 2 zealots (9 total)",                                                                              				  "time":"4:14"},
    {"text":"39 pylon at natural to make wallin",                                                                           		  "time":"4:22"},
    {"text":"39 probe (22)",                                                                     		                         		  "time":"4:28"},
    {"text":"40 gas at main)",                                                                                              		  "time":"4:32"},
    {"text":"40 probe (23)",                                                                     		                         		  "time":"4:39"},
    {"text":"41 complete wallin at natural using zealots",                                                                   		  "time":"4:45"},
    {"text":"41 probe (24) and continue scouting with probe to check ling numbers",       				                            	  "time":"4:51"},
    {"text":"42 core at main if enemy has a sunken and isn't going all-in (make more zealots in case he is going all-in)",     	  "time":"4:53"},
    {"text":"42 send 9 probes to natural minerals",                                                                            	  "time":"5:01"},
    {"text":"42 send 3 probes to gas",                                                                     	                 		  "time":"5:02"},
    {"text":"42 probe at main (25)",                                                                                              "time":"5:06"},
    {"text":"43 make 2 zealots (scouting probe dies)",                                                                            "time":"5:10"},
    {"text":"46 probe at natural (25) and check if he has speedlings to get ahead in tech",                                       "time":"5:15"},
    {"text":"47 probe at main (26)",                                                                                              "time":"5:20"},
    {"text":"48 probe at natural (27)",                                                                                           "time":"5:27"},
    {"text":"49 forge at main",                                                                                                   "time":"5:28"},
    {"text":"49 probe at main (28)",                                                                                              "time":"5:34"},
    {"text":"50 probe at natural (29)",                                                                                           "time":"5:39"},
    {"text":"51 stargate",                                                                                                  		  "time":"5:41"},
    {"text":"51 gas at natural",                                                                                              	  "time":"5:43"},
    {"text":"51 probe at main (30)",                                                                                              "time":"5:47"},
    {"text":"52 probe at natural (31)",                                                                                           "time":"5:53"},
    {"text":"53 pylon at natural",                                                                                                "time":"5:55"},
    {"text":"53 make 2 dragoons to kill overlord and defend vs mutas",                                                            "time":"6:04"},
    {"text":"57 cannon at natural and send 3 probes to natural gas",                                                              "time":"6:09"},
    {"text":"57 probe at main (32)",                                                                                              "time":"6:14"},
    {"text":"58 probe at natural (33)",                                                                                           "time":"6:14"},
    {"text":"59 +1 ground weapons",                                                                                               "time":"6:18"},
    {"text":"59 probe at main (34)",                                                                                              "time":"6:29"},
    {"text":"60 probe at natural (35)",                                                                                           "time":"6:29"},
    {"text":"61 1st corsair",                                                                                                     "time":"6:31"},
    {"text":"63 pylon at main",                                                                                                   "time":"6:34"},
    {"text":"63 probe at main (36)",                                                                                              "time":"6:42"},
    {"text":"64 probe at natural (37)",                                                                                           "time":"6:42"},
    {"text":"65 pylon at main",                                                                                                   "time":"6:43"},
    {"text":"65 probe at main (38)",                                                                                              "time":"6:54"},
    {"text":"66 probe at natural (39)",                                                                                           "time":"6:54"},
    {"text":"67 make 2 zealots",                                                                                                  "time":"6:56"},
    {"text":"71 2nd corsair and scout with the first one path to his natural to check if 3HH",                                    "time":"7:00"},
    {"text":"73 citadel",                                                                                                         "time":"7:05"},
    {"text":"73 pylon at natural",                                                                                                "time":"7:08"},
    {"text":"73 probe at main (40)",                                                                                              "time":"7:10"},
    {"text":"74 probe at natural (41)",                                                                                           "time":"7:10"},
    {"text":"75 probe at main (42)",                                                                                              "time":"7:22"},
    {"text":"76 probe at natural (43)",                                                                                           "time":"7:22"},
    {"text":"77 3rd corsair",                                                                                                     "time":"7:26"},
    {"text":"79 if he is going 5HH make 2 more zealots and stop corsair production",                                              "time":"7:30"},
    {"text":"83 make 2 more gateways",                                                                                            "time":"7:40"},
    {"text":"83 probe at main (44)",                                                                                              "time":"7:44"},
    {"text":"84 probe at natural (45)",                                                                                           "time":"7:44"},
    {"text":"85 pylon at main",                                                                                                   "time":"7:48"},
    {"text":"85 research zealot speed",                                                                                           "time":"7:50"},
    {"text":"85 templar archives",                                                                                                "time":"7:57"},
    {"text":"85 pylon at main",                                                                                                   "time":"8:00"},
    {"text":"85 probe at main (46)",                                                                                              "time":"8:05"},
    {"text":"86 probe at natural (47)",                                                                                           "time":"8:05"},
    {"text":"87 make 2 zealots",                                                                                                  "time":"8:11"},
    {"text":"91 kill overlords with corsairs and move out with army to kill his 3rd expo",                                        "time":"8:15"},
    {"text":"91 make a cannon and 2 pylons at natural",                                                                           "time":"8:18"},
    {"text":"91 make 4 zealots",                                                                                                  "time":"8:38"},
    {"text":"99 research storm",                                                                                                  "time":"8:42"},
    {"text":"99 pylon at main",                                                                                                   "time":"8:46"},
    {"text":"99 make 4 high templars",                                                                                            "time":"9:04"},
    {"text":"107 4 more gateways and a pylon",                                                                                    "time":"9:10"},
    {"text":"107 +2 ground weapons",                                                                                              "time":"9:17"},
    {"text":"107 probe at main (48)",                                                                                             "time":"9:24"},
    {"text":"108 probe at natural (49)",                                                                                          "time":"9:24"},
    {"text":"109 research goon range",                                                                                            "time":"9:32"},
    {"text":"109 probe at main (50)",                                                                                             "time":"9:36"},
    {"text":"110 probe at natural (51)",                                                                                          "time":"9:36"},
    {"text":"111 robotics",                                                                                                       "time":"9:54"},
    {"text":"END OF BUILD ORDER",                                                                                                 "time":"10:04"}
  ]
}
