{
  "Title": "9 Gate into +1G 7 30 11 SpeedLots 4 Sairs vs Overpool 2 lings (Dragon) (vs. Zerg)",
  "Link": "from replay",
  "secondsDelayed": -5,
  "buildSteps":[
    {"text":"4 probe (5) and split probes",                                                                                       "time":"0:05"},
    {"text":"5 probe (6)",                                                                                                        "time":"0:16"},
    {"text":"6 probe (7)",                                                                                                        "time":"0:29"},
    {"text":"7 75% send a probe to natural",                                                                                      "time":"0:38"},
    {"text":"7 probe (8)",                                                                                                        "time":"0:42"},
    {"text":"8 pylon and send it to scout 1st overlord and return it to natural",                                                 "time":"0:48"},
    {"text":"8 probe (9)",                                                                                                        "time":"0:55"},
    {"text":"9 gateway and send it to scout the other near main if you didn't find 1st overlord",                                 "time":"1:14"},
    {"text":"9 probe (10)",                                                                                                       "time":"1:19"},
    {"text":"10 probe (11)",                                                                                                      "time":"1:32"},
    {"text":"11 pylon at main near nexus",                                                                                        "time":"1:35"},
    {"text":"11 probe (12)",                                                                                                      "time":"1:44"},
    {"text":"12 1st zealot",                                                                                                      "time":"1:56"},
    {"text":"14 probe (13)",                                                                                                      "time":"1:57"},
    {"text":"15 probe (14)",                                                                                                      "time":"2:10"},
    {"text":"16 2nd zealot and send the 1st to pressure",                                                                         "time":"2:22"},
    {"text":"18 probe (15)",                                                                                                      "time":"2:23"},
    {"text":"19 probe (16)",                                                                                                      "time":"2:36"},
    {"text":"20 3rd zealot and keep sending zealots",                                                                             "time":"2:47"},
    {"text":"22 probe (17) and ~280 minerals send a probe to natural",                                                            "time":"2:48"},
    {"text":"23 nexus and send it to mine natural or block entrance",                                                             "time":"3:00"},
    {"text":"23 pylon at natural",                                                                                                "time":"3:06"},
    {"text":"23 4th zealot keep at wall",                                                                                         "time":"3:14"},
    {"text":"25 gas and send scout to scout the 3rd hatchery",                                                                    "time":"3:21"},
    {"text":"25 probe at main (18)",                                                                                              "time":"3:32"},
    {"text":"26 5th zealot keep at wall",                                                                                         "time":"3:40"},
    {"text":"28 forge at natural to complete wall",                                                                               "time":"3:42"},
    {"text":"28 probe at main (19)",                                                                                              "time":"3:45"},
    {"text":"29 send 3 probes to gas",                                                                                            "time":"3:55"},
    {"text":"29 core at main",                                                                                                    "time":"3:58"},
    {"text":"29 probe at main and ~700 health send 6 probes to natural minerals (20)",                                            "time":"4:03"},
    {"text":"30 1st cannon at natural",                                                                                           "time":"4:14"},
    {"text":"30 probe at main (21)",                                                                                              "time":"4:17"},
    {"text":"31 probe at natural (22)",                                                                                           "time":"4:20"},
    {"text":"32 probe at main (23)",                                                                                              "time":"4:30"},
    {"text":"33 probe at natural (24)",                                                                                           "time":"4:34"},
    {"text":"34 stargate",                                                                                                        "time":"4:40"},
    {"text":"34 probe at main (25)",                                                                                              "time":"4:44"},
    {"text":"35 probe at natural (26)",                                                                                           "time":"4:50"},
    {"text":"36 +1 ground weapons",                                                                                               "time":"4:51"},
    {"text":"36 6th zealot",                                                                                                      "time":"4:57"},
    {"text":"38 pylon at main for gateways",                                                                                      "time":"5:00"},
    {"text":"38 probe at main (27)",                                                                                              "time":"5:03"},
    {"text":"39 probe at natural (28)",                                                                                           "time":"5:05"},
    {"text":"40 citadel",                                                                                                         "time":"5:13"},
    {"text":"40 gas at natural",                                                                                                  "time":"5:17"},
    {"text":"40 probe at main (29)",                                                                                              "time":"5:19"},
    {"text":"41 probe at natural (30)",                                                                                           "time":"5:21"},
    {"text":"42 7th zealot",                                                                                                      "time":"5:26"},
    {"text":"44 1st corsair",                                                                                                     "time":"5:33"},
    {"text":"46 probe at main (31)",                                                                                              "time":"5:35"},
    {"text":"47 probe at natural (32)",                                                                                           "time":"5:37"},
    {"text":"48 pylon at natural for robotics",                                                                                   "time":"5:40"},
    {"text":"48 send 3 probes to natural gas",                                                                                    "time":"5:45"},
    {"text":"48 probe at main (33)",                                                                                              "time":"5:49"},
    {"text":"49 probe at natural (34)",                                                                                           "time":"5:50"},
    {"text":"50 research zealot speed",                         								                                                  "time":"5:57"},
    {"text":"50 pylon at main for gateways",                                                                                      "time":"5:58"},
    {"text":"50 8th zealot",                                                                                                      "time":"6:06"},
    {"text":"52 2nd corsair",                                                                                                     "time":"6:08"},
    {"text":"54 probe at main (35)",                                                                                              "time":"6:09"},
    {"text":"55 probe at natural (36)",                                                                                           "time":"6:10"},
    {"text":"56 2nd gateway at natural",                                                                                          "time":"6:17"},
    {"text":"56 probe at main (37)",                                                                                              "time":"6:22"},
    {"text":"57 probe at natural (38)",                                                                                           "time":"6:23"},
    {"text":"58 9th zealot",                                                                                                      "time":"6:31"},
    {"text":"60 3rd corsair",                                                                                                     "time":"6:32"},
    {"text":"62 pylon at main to spot drops or mutas",                                                                            "time":"6:36"},
    {"text":"62 probe at main (39)",                                                                                              "time":"6:38"},
    {"text":"63 probe at natural (40)",                                                                                           "time":"6:40"},
    {"text":"64 pylon at main",                                                                                                   "time":"6:43"},
    {"text":"64 templar archives",                                                                                                "time":"6:50"},
    {"text":"64 probe at main (41)",                                                                                              "time":"6:54"},
    {"text":"65 probe at natural (42)",                                                                                           "time":"6:55"},
    {"text":"66 make 2 zealots",                                                                                                  "time":"7:00"},
    {"text":"70 4th corsair",                                                                                                     "time":"7:05"},
    {"text":"72 probe at main (43)",                                                                                              "time":"7:10"},
    {"text":"73 probe at natural (44)",                                                                                           "time":"7:11"},
    {"text":"74 pylon at natural",                                                                                                "time":"7:12"},
    {"text":"74 2nd cannon at natural",                                                                                           "time":"7:19"},
    {"text":"74 make 2 high templars",                                                                                            "time":"7:30"},
    {"text":"78 make 2 more gateways",                                                                                            "time":"7:32"},
    {"text":"78 research storm",                                                                                                  "time":"7:42"},
    {"text":"78 2 pylons at main",                                                                                                "time":"7:44"},
    {"text":"78 5th corsair",                                                                                                     "time":"7:53"},
    {"text":"80 +1 air weapons",                                                                                                  "time":"8:03"},
    {"text":"END OF BUILD ORDER",                                                                                                 "time":"8:13"}
  ]
}
