{
  "Title": "11 Forge into +1G +1A 7:30 into midgame (Jaeyun) (vs. Zerg)",
  "Link": "https://www.youtube.com/watch?v=Li_WUp6pEpU",
  "secondsDelayed": -5,
  "buildSteps":[
    {"text":"4 probe (5) and split probes",                                                                                       "time":"0:05"},
    {"text":"5 probe (6)",                                                                                                        "time":"0:16"},
    {"text":"6 probe (7)",                                                                                                        "time":"0:29"},
    {"text":"7 75% send a probe to natural",                                                                                      "time":"0:38"},
    {"text":"7 probe (8)",                                                                                                        "time":"0:42"},
    {"text":"8 pylon and send it to mine natural and after it returns to main send it to mine main",                              "time":"0:50"},
    {"text":"8 probe (9)",                                                                                                        "time":"0:57"},
    {"text":"9 probe (10)",                                                                                                       "time":"1:12"},
    {"text":"10 probe (11) and send the 10th probe to natural",                                                                   "time":"1:25"},
    {"text":"11 forge and send it to scout horizontically on circuit breakers",                                                   "time":"1:35"},
    {"text":"11 probe (12)",                                                                                                      "time":"1:38"},
    {"text":"12 probe (13)",                                                                                                      "time":"1:51"},
    {"text":"12 ~280 minerals send a probe to natural",                                                                           "time":"1:57"},
    {"text":"13 nexus",                                                                                                           "time":"2:09"},
    {"text":"13 1st cannon at natural and send the probe to block entrance or as a 2nd scout",                                    "time":"2:21"},
    {"text":"13 probe (14)",                                                                                                      "time":"2:26"},
    {"text":"14 probe (15)",                                                                                                      "time":"2:39"},
    {"text":"15 gateway at natural to complete wall",                                                                             "time":"2:49"},
    {"text":"15 probe (16)",                                                                                                      "time":"2:51"},
    {"text":"16 gas",                                                                                                             "time":"2:58"},
    {"text":"16 probe (17)",                                                                                                      "time":"3:04"},
    {"text":"17 ~700 health send 5 probes to natural minerals",                                                                   "time":"3:16"},
    {"text":"17 probe at main (18)",                                                                                              "time":"3:28"},
    {"text":"18 probe at natural (19)",                                                                                           "time":"3:28"},
    {"text":"19 core at natural and send 3 probes to gas and send scout to scout the 3rd hatchery",                               "time":"3:29"},
    {"text":"19 1st zealot",                                                                                                      "time":"3:32"},
    {"text":"21 probe at main (20)",                                                                                              "time":"3:41"},
    {"text":"22 probe at natural (21)",                                                                                           "time":"3:41"},
    {"text":"23 pylon at main",                                                                                                   "time":"3:42"},
    {"text":"23 probe at main (22)",                                                                                              "time":"3:54"},
    {"text":"24 probe at natural (23)",                                                                                           "time":"3:54"},
    {"text":"25 gas at natural",                                                                                                  "time":"4:00"},
    {"text":"25 probe at main (24)",                                                                                              "time":"4:08"},
    {"text":"26 probe at natural (25)",                                                                                           "time":"4:08"},
    {"text":"27 2nd zealot",                                                                                                      "time":"4:09"},
    {"text":"29 stargate",                                                                                                        "time":"4:15"},
    {"text":"29 probe at main (26)",                                                                                              "time":"4:19"},
    {"text":"30 probe at natural (27)",                                                                                           "time":"4:19"},
    {"text":"31 pylon at natural and send 3 probes to natural gas",                                                               "time":"4:26"},
    {"text":"31 probe at main (28)",                                                                                              "time":"4:32"},
    {"text":"32 3rd zealot",                                                                                                      "time":"4:34"},
    {"text":"34 +1 ground weapons and +1 air weapons",                                                                            "time":"4:40"},
    {"text":"34 probe at main (29)",                                                                                              "time":"4:47"},
    {"text":"35 probe at natural (30)",                                                                                           "time":"4:47"},
    {"text":"36 pylon at main (start blocking a probe)",                                                                          "time":"4:58"},
    {"text":"36 4th zealot",                                                                                                      "time":"5:00"},
    {"text":"38 probe at main (31)",                                                                                              "time":"5:01"},
    {"text":"39 probe at natural (32)",                                                                                           "time":"5:01"},
    {"text":"40 1st corsair",                                                                                                     "time":"5:07"},
    {"text":"42 probe at main (31)",                                                                                              "time":"5:20"},
    {"text":"43 probe at natural (32)",                                                                                           "time":"5:18"},
    {"text":"44 citadel",                                                                                                         "time":"5:20"},
    {"text":"44 5th zealot",                                                                                                      "time":"5:26"},
    {"text":"46 2nd corsair and send 1st corsair to scout his natural gas",               				                                "time":"5:30"},
    {"text":"48 probe at main (33)",                                                                                              "time":"5:33"},
    {"text":"49 probe at natural (34)",                                                                                           "time":"5:33"},
    {"text":"50 pylon for gateways",                                                                                              "time":"5:37"},
    {"text":"50 pylon (end blocking a probe)",                                                                                    "time":"5:57"},
    {"text":"50 3rd corsair and send 2nd corsair to other area of map to kill overlord",               			                      "time":"6:00"},
    {"text":"52 research zealot speed",                         								                                                  "time":"6:01"},
    {"text":"52 probe at main (35)",                                                                                              "time":"6:03"},
    {"text":"53 probe at natural (36)",                                                                                           "time":"6:03"},
    {"text":"54 pylon at natural for cannons and rally corsairs back at natural",                                                 "time":"6:06"},
    {"text":"54 6th zealot",                                                                                 			                "time":"6:09"},
    {"text":"56 probe at main (37)",                                                                                              "time":"6:15"},
    {"text":"57 probe at natural (38)",                                                                                           "time":"6:15"},
    {"text":"58 4th corsair and cannon near stargate",                                                                            "time":"6:26"},
    {"text":"60 probe at main (39)",                                                                                              "time":"6:30"},
    {"text":"61 probe at natural (40)",                                                                                           "time":"6:30"},
    {"text":"62 6th zealot and templar archives",                                                                                 "time":"6:33"},
    {"text":"64 probe at main (41)",                                                                                              "time":"6:40"},
    {"text":"65 probe at natural (42)",                                                                                           "time":"6:40"},
    {"text":"66 5th corsair",                                                                                                     "time":"6:51"},
    {"text":"68 2nd gateway",                                                                                                     "time":"6:54"},
    {"text":"68 pylon at natural for robotics",                                                                                   "time":"6:57"},
    {"text":"68 7th zealot",                                                                                                      "time":"7:00"},
    {"text":"70 pylon at gateways",                                                                                               "time":"7:09"},
    {"text":"70 pylon for new gateways",                                                                                          "time":"7:20"},
    {"text":"70 2nd cannon at natural",                                                                                           "time":"7:20"},
    {"text":"70 research storm",                                                                                                  "time":"7:23"},
    {"text":"70 1st high templar at 1st gateway",                                                                                 "time":"7:24"},
    {"text":"72 +2 ground weapons",                                                                                               "time":"7:30"},
    {"text":"END OF BUILD ORDER",                                                                                                 "time":"7:40"}
  ]
}
