{
  "Title": "12 Forge into +1G +1A 7:30 into midgame (Beast) (vs. Zerg)",
  "Link": "https://www.youtube.com/watch?v=Wrt_vrHJscQ",
  "secondsDelayed": -5,
  "buildSteps":[
    {"text":"4 probe (5) and split probes",                                                                                       "time":"0:05"},
    {"text":"5 probe (6)",                                                                                                        "time":"0:16"},
    {"text":"6 probe (7)",                                                                                                        "time":"0:29"},
    {"text":"7 75% send a probe to natural",                                                                                      "time":"0:38"},
    {"text":"7 probe (8)",                                                                                                        "time":"0:42"},
    {"text":"8 pylon and send it to mine natural and after it returns to main send it to mine main",                              "time":"0:50"},
    {"text":"8 probe (9)",                                                                                                        "time":"0:57"},
    {"text":"9 probe (10)",                                                                                                       "time":"1:12"},
    {"text":"10 probe (11)",                                                                                                      "time":"1:25"},
    {"text":"11 probe (12) and send the 11th probe to natural",                                                                   "time":"1:40"},
    {"text":"12 forge and send it to scout horizontically on circuit breakers",                                                   "time":"1:48"},
    {"text":"12 probe (13) and send the 13th probe to natural",                                                                   "time":"1:51"},
    {"text":"13 nexus",                                                                                                           "time":"2:14"},
    {"text":"13 1st cannon at natural",                                                                                           "time":"2:25"},
    {"text":"13 probe (14)",                                                                                                      "time":"2:28"},
    {"text":"14 probe (15)",                                                                                                      "time":"2:41"},
    {"text":"15 gateway at natural to complete wall",                                                                             "time":"2:51"},
    {"text":"15 probe (16)",                                                                                                      "time":"2:54"},
    {"text":"16 pylon at main",                                                                                                   "time":"2:59"},
    {"text":"16 probe (17)",                                                                                                      "time":"3:06"},
    {"text":"17 gas",                                                                                                             "time":"3:10"},
    {"text":"17 probe (18) and send 5 probes to natural minerals",                                                                "time":"3:20"},
    {"text":"18 probe at natural (19)",                                                                                           "time":"3:33"},
    {"text":"19 probe at main (20)",                                                                                              "time":"3:35"},
    {"text":"20 core at main and send 3 probes to gas and send scout to scout the 3rd hatchery",                                  "time":"3:39"},
    {"text":"20 1st zealot",                                                                                                      "time":"3:44"},
    {"text":"22 probe at main (21)",                                                                                              "time":"3:52"},
    {"text":"23 probe at natural (22)",                                                                                           "time":"3:52"},
    {"text":"24 probe at main (23)",                                                                                              "time":"4:06"},
    {"text":"25 probe at natural (24)",                                                                                           "time":"4:06"},
    {"text":"26 2nd zealot",                                                                                                      "time":"4:11"},
    {"text":"28 probe at main (25)",                                                                                              "time":"4:19"},
    {"text":"29 probe at natural (26)",                                                                                           "time":"4:19"},
    {"text":"30 stargate",                                                                                                        "time":"4:21"},
    {"text":"30 gas at natural",                                                                                                  "time":"4:30"},
    {"text":"30 3rd zealot and pylon",                                                                                            "time":"4:36"},
    {"text":"32 +1 ground weapons",                                                                                               "time":"4:40"},
    {"text":"32 probe at main (27)",                                                                                              "time":"4:41"},
    {"text":"33 probe at natural (28)",                                                                                           "time":"4:44"},
    {"text":"34 +1 air weapons and send 3 probes to natural gas",                                                                 "time":"4:55"},
    {"text":"34 probe at main (29)",                                                                                              "time":"4:57"},
    {"text":"35 probe at natural (30)",                                                                                           "time":"4:57"},
    {"text":"36 4th zealot",                                                                                                      "time":"5:01"},
    {"text":"38 pylon at main",                                                                                                   "time":"5:05"},
    {"text":"38 probe at main (31)",                                                                                              "time":"5:10"},
    {"text":"39 probe at natural (32)",                                                                                           "time":"5:10"},
    {"text":"40 1st corsair",                                                                                                     "time":"5:12"},
    {"text":"42 citadel",                                                                                                         "time":"5:25"},
    {"text":"42 5th zealot",                                                                                                      "time":"5:26"},
    {"text":"44 probe at main (33)",                                                                                              "time":"5:30"},
    {"text":"45 probe at natural (34)",                                                                                           "time":"5:30"},
    {"text":"46 pylon (scouting probe dies)",                                                                                     "time":"5:37"},
    {"text":"45 2nd corsair and send 1st corsair to scout and maybe kill an overlord there",                                      "time":"5:41"},
    {"text":"47 2nd gateway at natural and move out with 5 zealots if he doesn't have defenses at the 3rd",                       "time":"5:47"},
    {"text":"47 probe at main (34)",                                                                                              "time":"5:57"},
    {"text":"48 probe at natural (35)",                                                                                           "time":"5:57"},
    {"text":"49 pylon (start blocking a probe) and 3rd corsair and send 2nd corsair to other area of map to kill overlord",       "time":"6:07"},
    {"text":"51 research zealot speed and after corsairs kill some overlords rally them back at natural",                         "time":"6:08"},
    {"text":"51 6th zealot and templar archives",                                                                                 "time":"6:19"},
    {"text":"53 cannon near stargate",                                                                                            "time":"6:25"},
    {"text":"53 probe at main (36)",                                                                                              "time":"6:40"},
    {"text":"54 probe at natural (37)",                                                                                           "time":"6:40"},
    {"text":"55 7th zealot at 2nd gateway",                                                                                       "time":"6:41"},
    {"text":"57 8th zealot at 1st gateway",                                                                                       "time":"6:45"},
    {"text":"59 4th corsair",                                                                                                     "time":"6:46"},
    {"text":"61 pylon (end blocking a probe)",                                                                                    "time":"6:49"},
    {"text":"61 2nd cannon at natural",                                                                                           "time":"7:00"},
    {"text":"61 probe at main (38)",                                                                                              "time":"7:07"},
    {"text":"62 probe at natural (39)",                                                                                           "time":"7:07"},
    {"text":"63 1st high templar at 2nd gateway",                                                                                 "time":"7:09"},
    {"text":"65 2nd high templar at 1st gateway",                                                                                 "time":"7:09"},
    {"text":"67 research storm (1st zealot dies)",                                                                                "time":"7:18"},
    {"text":"65 probe at main (40)",                                                                                              "time":"7:20"},
    {"text":"66 probe at natural (41)",                                                                                           "time":"7:20"},
    {"text":"67 pylon at main",                                                                                                   "time":"7:28"},
    {"text":"67 probe at main (42)",                                                                                              "time":"7:32"},
    {"text":"68 probe at natural (43)",                                                                                           "time":"7:32"},
    {"text":"69 5th corsair (4 zealots die)",                                                                                     "time":"7:33"},
    {"text":"63 3rd cannon at natural",                                                                                           "time":"7:41"},
    {"text":"63 3rd high templar at 2nd gateway",                                                                                 "time":"7:44"},
    {"text":"65 probe at main (44)",                                                                                              "time":"7:45"},
    {"text":"66 probe at natural (45)",                                                                                           "time":"7:45"},
    {"text":"67 3rd gateway",                                                                                                     "time":"7:50"},
    {"text":"67 probe at main (46)",                                                                                              "time":"7:58"},
    {"text":"68 probe at natural (47)",                                                                                           "time":"7:58"},
    {"text":"69 6th corsair",                                                                                                     "time":"7:58"},
    {"text":"71 4th gateway",                                                                                                     "time":"8:03"},
    {"text":"71 pylon at main",                                                                                                   "time":"8:07"},
    {"text":"71 +2 ground weapons",                                                                                               "time":"8:10"},
    {"text":"71 5th gateway and keep making corsairs if you lose them until you have at least 5",                                 "time":"8:15"},
    {"text":"71 probe at main (48)",                                                                                              "time":"8:29"},
    {"text":"72 probe at natural (49)",                                                                                           "time":"8:29"},
    {"text":"73 1 high templar and 1 zealot",                                                                                     "time":"8:31"},
    {"text":"77 6th gateway",                                                                                                     "time":"8:35"},
    {"text":"77 pylon at main",                                                                                                   "time":"8:37"},
    {"text":"77 make 2 zealots from 3th and 4th gateways",                                                                        "time":"8:50"},
    {"text":"77 robotics",                                                                                                        "time":"8:54"},
    {"text":"81 2 pylons at main",                                                                                                "time":"8:56"},
    {"text":"81 probe at main (50)",                                                                                              "time":"9:03"},
    {"text":"82 probe at natural (51)",                                                                                           "time":"9:03"},
    {"text":"83 research goon range and scout with corsairs",                                                                     "time":"9:06"},
    {"text":"83 make 2 more zealots from 3rd and 4th gateway and move out with zealots",                                          "time":"9:14"},
    {"text":"87 make 6 dragoons",                                                                                                 "time":"9:35"},
    {"text":"99 probe at main (52)",                                                                                              "time":"9:56"},
    {"text":"100 probe at natural (53)",                                                                                          "time":"9:56"},
    {"text":"101 pylon at main",                                                                                                  "time":"9:56"},
    {"text":"101 observatory",                                                                                                    "time":"9:59"},
    {"text":"101 7th corsair and send a probe to take 3rd expo",                                                                  "time":"10:00"},
    {"text":"101 make 6 dragoons or zealots if low on gas",                                                                       "time":"10:10"},
    {"text":"113 take a 3rd expo and build 2 pylons near it",                                                                     "time":"10:27"},
    {"text":"113 observers",                                                                                                      "time":"10:30"},
    {"text":"114 make 4 dragoons or zealots if low on gas",                                                                       "time":"10:46"},
    {"text":"122 pylon at 3rd",                                                                                                   "time":"10:52"},
    {"text":"122 make a cannon at 3rd",                                                                                           "time":"11:05"},
    {"text":"122 make 6 dragoon or zealots if low on gas",                                                                        "time":"11:17"},
    {"text":"134 when +2 ground weapons is done move out with whole army ",                                                       "time":"11:30"},
    {"text":"xx make 2 more cannons at 3rd and transfer 10 probes from main and 3 from natural and make 2 more pylons there",     "time":"11:40"},
    {"text":"xx 2 more gateways",                                                                                                 "time":"12:10"},
    {"text":"xx keep making high templars and dragoons and zealots if low on gas",                                                "time":"12:13"},
    {"text":"xx storm enemy army, never commit unless you are ready, scout with corsair for possible hidden 4th",                 "time":"13:00"},
    {"text":"xx 2 more gateways and 2 pylons",                                                                                    "time":"13:23"},
    {"text":"xx when you are fighting only make zealots and careful for flanks",                                                  "time":"13:45"},
    {"text":"xx take a 4th if you are winning the fight and build 2 pylons there and 2 cannons",                                  "time":"14:20"},
    {"text":"xx research templar energy",                                                                                         "time":"15:00"}
  ]
}
