{
  "Title": "9 Gate into +1G 7 30 12 SpeedLots 4 Sairs vs Overpool 6 lings (Dragon) (vs. Zerg)",
  "Link": "from replay",
  "secondsDelayed": -5,
  "buildSteps":[
    {"text":"4 probe (5) and split probes",                                                                                       "time":"0:05"},
    {"text":"5 probe (6)",                                                                                                        "time":"0:16"},
    {"text":"6 probe (7)",                                                                                                        "time":"0:29"},
    {"text":"7 75% send a probe to natural",                                                                                      "time":"0:38"},
    {"text":"7 probe (8)",                                                                                                        "time":"0:42"},
    {"text":"8 pylon and send it to scout 1st overlord and return it to natural",                                                 "time":"0:48"},
    {"text":"8 probe (9)",                                                                                                        "time":"0:55"},
    {"text":"9 gateway and send it to scout the other near main if you didn't find 1st overlord",                                 "time":"1:15"},
    {"text":"9 probe (10)",                                                                                                       "time":"1:18"},
    {"text":"10 probe (11)",                                                                                                      "time":"1:30"},
    {"text":"11 pylon at main near nexus",                                                                                        "time":"1:35"},
    {"text":"11 probe (12)",                                                                                                      "time":"1:44"},
    {"text":"12 1st zealot",                                                                                                      "time":"1:56"},
    {"text":"14 probe (13)",                                                                                                      "time":"1:57"},
    {"text":"15 probe (14)",                                                                                                      "time":"2:10"},
    {"text":"16 2nd zealot and keep the 1st at wall",                                                                             "time":"2:21"},
    {"text":"18 probe (15)",                                                                                                      "time":"2:22"},
    {"text":"19 probe (16)",                                                                                                      "time":"2:34"},
    {"text":"20 3rd zealot and keep them at the wall",                                                                            "time":"2:47"},
    {"text":"22 probe (17) and ~280 minerals send a probe to natural",                                                            "time":"2:48"},
    {"text":"23 nexus and send it to mine natural or block entrance",                                                             "time":"3:00"},
    {"text":"23 pylon at natural",                                                                                                "time":"3:06"},
    {"text":"23 4th zealot",                                                                                                      "time":"3:14"},
    {"text":"25 forge at natural to complete wall",                                                                               "time":"3:23"},
    {"text":"25 probe at main (18)",                                                                                              "time":"3:30"},
    {"text":"26 5th zealot",                                                                                                      "time":"3:38"},
    {"text":"28 gas and send scout to scout the 3rd hatchery",                                                                    "time":"3:39"},
    {"text":"28 probe at main (19)",                                                                                              "time":"3:45"},
    {"text":"29 1st cannon at natural",                                                                                           "time":"3:54"},
    {"text":"29 probe at main (20)",                                                                                              "time":"3:58"},
    {"text":"30 6th zealot and ~700 health send 6 probes to natural minerals",                                                    "time":"4:04"},
    {"text":"32 send 3 probes to gas",                                                                                            "time":"4:09"},
    {"text":"32 probe at main (21)",                                                                                              "time":"4:10"},
    {"text":"33 core at main",                                                                                                    "time":"4:21"},
    {"text":"33 probe at main (22)",                                                                                              "time":"4:23"},
    {"text":"34 probe at natural (23)",                                                                                           "time":"4:28"},
    {"text":"35 +1 ground weapons",                                                                                               "time":"4:37"},
    {"text":"35 probe at main (24)",                                                                                              "time":"4:39"},
    {"text":"36 probe at natural (25)",                                                                                           "time":"4:42"},
    {"text":"37 gas at natural",                                                                                                  "time":"4:45"},
    {"text":"37 probe at main (26)",                                                                                              "time":"4:52"},
    {"text":"38 probe at natural (27)",                                                                                           "time":"4:54"},
    {"text":"39 pylon at main for gateways",                                                                                      "time":"4:55"},
    {"text":"39 probe at main (28)",                                                                                              "time":"5:05"},
    {"text":"40 probe at natural (29)",                                                                                           "time":"5:06"},
    {"text":"41 stargate",                                                                                                        "time":"5:07"},
    {"text":"41 send 3 probes to natural gas",                                                                                    "time":"5:10"},
    {"text":"41 7th zealot and citadel",                                                                                          "time":"5:21"},
    {"text":"43 probe at main (30)",                                                                                              "time":"5:23"},
    {"text":"44 probe at natural (31)",                                                                                           "time":"5:24"},
    {"text":"45 pylon at main for gateways",                                                                                      "time":"5:27"},
    {"text":"45 2nd gateway at natural",                                                                                          "time":"5:35"},
    {"text":"45 probe at main (32)",                                                                                              "time":"5:37"},
    {"text":"46 probe at natural (33)",                                                                                           "time":"5:39"},
    {"text":"47 8th zealot",                                                                                                      "time":"5:46"},
    {"text":"49 probe at main (34)",                                                                                              "time":"5:54"},
    {"text":"50 probe at natural (35)",                                                                                           "time":"5:55"},
    {"text":"51 1st corsair (scouting probe dies)",                                                                               "time":"5:56"},
    {"text":"52 research zealot speed",                         								                                                  "time":"6:03"},
    {"text":"52 pylon at natural for robotics",                                                                                   "time":"6:05"},
    {"text":"52 probe at main (35)",                                                                                              "time":"6:08"},
    {"text":"53 probe at natural (36)",                                                                                           "time":"6:09"},
    {"text":"54 make 2 zealots",                                                                                                  "time":"6:18"},
    {"text":"58 pylon at main to spot drops or mutas",                                                                            "time":"6:20"},
    {"text":"58 2nd corsair",                                                                                                     "time":"6:27"},
    {"text":"60 probe at main (37)",                                                                                              "time":"6:30"},
    {"text":"61 probe at natural (38)",                                                                                           "time":"6:31"},
    {"text":"62 templar archives",                                                                                                "time":"6:34"},
    {"text":"62 make 2 zealots",                                                                                                  "time":"6:44"},
    {"text":"66 2nd cannon at natural",                                                                                           "time":"6:50"},
    {"text":"66 probe at main (39)",                                                                                              "time":"6:52"},
    {"text":"67 probe at natural (40)",                                                                                           "time":"6:53"},
    {"text":"68 3rd corsair",                                                                                                     "time":"6:58"},
    {"text":"70 pylon at main for gateways",                                                                                      "time":"7:02"},
    {"text":"70 make 2  high templars",                                                                                           "time":"7:10"},
    {"text":"74 pylon at main",                                                                                                   "time":"7:11"},
    {"text":"78 research storm",                                                                                                  "time":"7:19"},
    {"text":"74 probe at main (41)",                                                                                              "time":"7:25"},
    {"text":"75 probe at natural (42)",                                                                                           "time":"7:26"},
    {"text":"76 4th corsair",                                                                                                     "time":"7:32"},
    {"text":"78 make 2 more gateways",                                                                                            "time":"7:38"},
    {"text":"78 probe at main (43)",                                                                                              "time":"7:41"},
    {"text":"79 probe at natural (44)",                                                                                           "time":"7:42"},
    {"text":"80 +1 air weapons",                                                                                                  "time":"7:45"},
    {"text":"END OF BUILD ORDER",                                                                                                 "time":"7:55"}
  ]
}
