{
  "Title": "5 Gate Goons (Best) (vs. Zerg)",
  "Link": "https://www.youtube.com/watch?app=desktop&v=Shmwg_Glwuk&feature=youtu.be",
  "secondsDelayed": -5,
  "buildSteps":[
    {"text":"4 probe (5) and split probes",                                                                                       "time":"0:05"},
    {"text":"5 probe (6)",                                                                                                        "time":"0:16"},
    {"text":"6 probe (7)",                                                                                                        "time":"0:29"},
    {"text":"7 75% send a probe to natural",                                                                                      "time":"0:38"},
    {"text":"7 probe (8)",                                                                                                        "time":"0:42"},
    {"text":"8 pylon and send it to scout vertically on circuit breakers",                                                        "time":"0:50"},
    {"text":"8 probe (9)",                                                                                                        "time":"0:57"},
    {"text":"9 probe (10)",                                                                                                       "time":"1:12"},
    {"text":"10 probe (11) and send the 10th probe to natural and 1st scout horizontically if you didn't find enemy",             "time":"1:25"},
    {"text":"11 forge and send it to scout horizontically on circuit breakers if 1st scout didn't find enemy",                    "time":"1:41"},
    {"text":"11 probe (12)",                                                                                                      "time":"1:42"},
    {"text":"12 probe (13)",                                                                                                      "time":"1:54"},
    {"text":"13 if you find enemy in cross position send a probe to natural and recall 2nd scout",                                "time":"2:05"},
    {"text":"13 nexus",                                                                                                           "time":"2:14"},
    {"text":"13 1st cannon at natural",                                                                                           "time":"2:26"},
    {"text":"13 probe (14)",                                                                                                      "time":"2:31"},
    {"text":"14 probe (15)",                                                                                                      "time":"2:44"},
    {"text":"15 gateway at natural to complete wall",                                                                             "time":"2:47"},
    {"text":"15 probe (16)",                                                                                                      "time":"2:57"},
    {"text":"16 pylon at main",                                                                                                   "time":"2:59"},
    {"text":"16 probe (17) and gas",                                                                                              "time":"3:10"},
    {"text":"17 probe (18) and send 4 probes to natural minerals",                                                                "time":"3:22"},
    {"text":"18 core at main",                                                                                                    "time":"3:32"},
    {"text":"18 probe at natural (19)",                                                                                           "time":"3:35"},
    {"text":"19 probe at main (20) and send 3 probes to gas",                                                                     "time":"3:38"},
    {"text":"20 1st zealot",                                                                                                      "time":"3:42"},
    {"text":"22 probe at natural (21)",                                                                                           "time":"3:47"},
    {"text":"23 probe at main and send it to natural minerals (21)",                                                              "time":"3:50"},
    {"text":"24 probe at natural (23)",                                                                                           "time":"4:00"},
    {"text":"25 probe at main and send it to natural minerals (24)",                                                              "time":"4:03"},
    {"text":"26 2nd zealot",                                                                                                      "time":"4:09"},
    {"text":"28 research goon range",                                                                                             "time":"4:13"},
    {"text":"28 probe at main (25)",                                                                                              "time":"4:18"},
    {"text":"29 probe at natural (26)",                                                                                           "time":"4:18"},
    {"text":"30 probe at main (27)",                                                                                              "time":"4:30"},
    {"text":"31 probe at natural (28)",                                                                                           "time":"4:30"},
    {"text":"32 pylon at main for gateways",                                                                                      "time":"4:31"},
    {"text":"32 +1 ground weapons",                                                                                               "time":"4:34"},
    {"text":"32 3rd zealot (scouting probe dies)",                                                                                "time":"4:39"},
    {"text":"33 probe at main (29)",                                                                                              "time":"4:53"},
    {"text":"34 probe at natural (30)",                                                                                           "time":"4:53"},
    {"text":"35 make 4 gateways",                                                                                                 "time":"4:58"},
    {"text":"35 1st dragoon",                                                                                                     "time":"5:15"},
    {"text":"37 pylon at main",                                                                                                   "time":"5:21"},
    {"text":"37 2nd cannon and another pylon at natural",                                                                         "time":"5:32"},
    {"text":"37 make 2 more dragoons",                                                                                            "time":"5:48"},
    {"text":"41 3rd cannon at natural and another dragoon",                                                                       "time":"5:54"},
    {"text":"43 make 2 more dragoons",                                                                                            "time":"5:58"},
    {"text":"47 make 2 more dragoons",                                                                                            "time":"6:19"},
    {"text":"51 keep making dragoon out of all the gateways",                                                                     "time":"6:25"},
    {"text":"xx pylon at natural and 2 pylons at main",                                                                           "time":"6:41"},
    {"text":"xx gas at natural",                                                                                                  "time":"6:55"},
    {"text":"xx when moving out keep poking enemy units and micro your dragoons",                                                 "time":"7:10"},
    {"text":"xx citadel and send 3 probes to natural gas",                                                                        "time":"7:23"}
  ]
}
