{
  "Title": "Fast Arbiter (Light) (vs. Terran)",
  "Link": "https://www.youtube.com/watch?v=97DiqbSkrk4",
  "secondsDelayed": -5,
  "buildSteps":[
    {"text":"4 probe (5) and split probes",                                                                                                                           "time":"0:05"},
    {"text":"5 probe (6)",                                                                                                                                            "time":"0:16"},
    {"text":"6 probe (7)",                                                                                                                                            "time":"0:29"},
    {"text":"7 probe (8)",                                                                                                                                            "time":"0:42"},
    {"text":"8 pylon",                                                                                                                                                "time":"0:50"},
    {"text":"8 probe (9)",                                                                                                                                            "time":"0:57"},
    {"text":"9 probe (10)",                                                                                                                                           "time":"1:12"},
    {"text":"10 gateway",                                                                                                                                             "time":"1:14"},
    {"text":"10 probe (11)",                                                                                                                                          "time":"1:22"},
    {"text":"11 probe (12)",                                                                                                                                          "time":"1:33"},
    {"text":"12 gas",                                                                                                                                                 "time":"1:34"},
    {"text":"12 probe (13)",                                                                                                                                          "time":"1:44"},
    {"text":"13 core",                                                                     									                                                          "time":"1:57"},
    {"text":"13 probe (14) and send 3 probes to gas",                                                                                                                 "time":"2:00"},
    {"text":"14 pylon (block outer minerals with this one)",                                                                                                          "time":"2:14"},
    {"text":"14 probe (15)",                                                                                                                                          "time":"2:15"},
    {"text":"15 probe (16)",                                                                                                                                          "time":"2:26"},
    {"text":"16 1st dragoon",                                                                                                                                         "time":"2:37"},
    {"text":"18 probe (17)",                                                                                                                                          "time":"2:38"},
    {"text":"19 research goon range",                                                                                                                                 "time":"2:47"},
    {"text":"19 probe (18)",                                                                                                                                          "time":"2:51"},
    {"text":"20 probe (19)",                                                                                                                                          "time":"3:04"},
    {"text":"21 2nd dragoon and scout with 1st dragoon and send the next probe to natural",                                                                           "time":"3:08"},
    {"text":"23 nexus",                                                                                                                                               "time":"3:31"},
    {"text":"23 pylon at natural to make wallin",                                                                                                                     "time":"3:39"},
    {"text":"23 probe (20), 1st dragoon at enemy natural, 2nd dragoon stays back",                                                                                    "time":"3:45"},
    {"text":"24 probe (21)",                                                                                                                                          "time":"3:57"},
    {"text":"25 robotics",                                                                                                                                            "time":"4:01"},
    {"text":"25 3rd dragoon",                                                                                                                                         "time":"4:08"},
    {"text":"27 probe (22)",                                                                                                                                          "time":"4:11"},
    {"text":"28 probe (23)",                                                                                                                                          "time":"4:24"},
    {"text":"29 2 more gateways",                                                                                                                                     "time":"4:30"},
    {"text":"29 probe (24)",                                                                                                                                          "time":"4:37"},
    {"text":"30 send 7 probes to natural minerals",                                                                                                                   "time":"4:41"},
    {"text":"30 4th dragoon",                                                                                                                                         "time":"4:45"},
    {"text":"32 probe at main (25)",                                                                                                                                  "time":"4:59"},
    {"text":"33 probe at natural (26)",                                                                                                                               "time":"4:59"},
    {"text":"34 observatory at natural to make wallin",                                                                                                               "time":"5:02"},
    {"text":"34 pylon at natural to make wallin",                                                                                                                     "time":"5:05"},
    {"text":"34 probe at main (27)",                                                                                                                                  "time":"5:10"},
    {"text":"35 probe at natural (28)",                                                                                                                               "time":"5:10"},
    {"text":"36 probe at main (29)",                                                                                                                                  "time":"5:25"},
    {"text":"37 probe at natural (30)",                                                                                                                               "time":"5:25"},
    {"text":"38 1st observer",                                                                                                                                        "time":"5:28"},
    {"text":"39 make 3 dragoons",                                                                                                                                     "time":"5:32"},
    {"text":"45 probe at main (31)",                                                                                                                                  "time":"5:37"},
    {"text":"46 probe at natural (32)",                                                                                                                               "time":"5:37"},
    {"text":"47 pylon at gateways",                                                                                                                                   "time":"5:38"},
    {"text":"47 probe at main (33)",                                                                                                                                  "time":"5:49"},
    {"text":"48 probe at natural (34)",                                                                                                                               "time":"5:49"},
    {"text":"49 2nd observer and send the 1st to scout",                                                                                                              "time":"5:54"},
    {"text":"50 gas at natural and defend main with dragoons if enemy is not coming out",                                                                             "time":"5:56"},
    {"text":"50 probe at main (35)",                                                                                                                                  "time":"6:00"},
    {"text":"51 probe at natural (36)",                                                                                                                               "time":"6:00"},
    {"text":"52 citadel or if enemy is going 4-6 factories make 8-10 gateways total and cut probes",                                                                  "time":"6:02"},
    {"text":"52 probe at main (37)",                                                                                                                                  "time":"6:12"},
    {"text":"53 probe at natural (38)",                                                                                                                               "time":"6:12"},
    {"text":"54 pylon at natural for cannons and send a probe to take a third",                                                                                       "time":"6:14"},
    {"text":"54 probe at main (39)",                                                                                                                                  "time":"6:25"},
    {"text":"55 probe at natural (40)",                                                                                                                               "time":"6:25"},
    {"text":"56 take a third expo and make a pylon there to make wallin (1st dragoon dies)",                                                                          "time":"6:31"},
    {"text":"54 send 3 probes to natural gas and if enemy is coming move out with your army",                                                                         "time":"6:36"},
    {"text":"54 make 3 dragoons and send 1st observer to scout enemy natural",                                                                                        "time":"6:41"},
    {"text":"60 probe at main (41)",                                                                                                                                  "time":"6:47"},
    {"text":"61 probe at natural (42)",                                                                                                                               "time":"6:47"},
    {"text":"62 stargate",                                                                                                                                            "time":"6:56"},
    {"text":"62 probe at main (43)",                                                                                                                                  "time":"7:01"},
    {"text":"63 probe at natural (44)",                                                                                                                               "time":"7:01"},
    {"text":"64 templar archives",                                                                                                                                    "time":"7:07"},
    {"text":"64 probe at main (45)",                                                                                                                                  "time":"7:12"},
    {"text":"65 probe at natural (46)",                                                                                                                               "time":"7:12"},
    {"text":"66 pylon at third for cannons",                                                                                                                          "time":"7:17"},
    {"text":"66 probe at main (47)",                                                                                                                                  "time":"7:25"},
    {"text":"67 probe at natural (48)",                                                                                                                               "time":"7:25"},
    {"text":"68 forge at third to make wallin and send 8 probes from main to third expo",                                                                             "time":"7:28"},
    {"text":"68 make 3 dragoons",                                                                                                                                     "time":"7:36"},
    {"text":"74 probe at main (49)",                                                                                                                                  "time":"7:39"},
    {"text":"75 probe at natural (50)",                                                                                                                               "time":"7:39"},
    {"text":"76 3rd observer and scout again the main with 1st observer",                                                                                             "time":"7:44"},
    {"text":"77 arbiter tribunal",                                                                                                                                    "time":"7:52"},
    {"text":"77 probe at main (51)",                                                                                                                                  "time":"7:54"},
    {"text":"78 probe at natural (52)",                                                                                                                               "time":"7:54"},
    {"text":"79 probe at third (53)",                                                                                                                                 "time":"7:54"},
    {"text":"80 2 more gateways and +1 ground weapons",                                                                                                               "time":"8:02"},
    {"text":"80 probe at main (54)",                                                                                                                                  "time":"8:08"},
    {"text":"81 probe at natural (55)",                                                                                                                               "time":"8:08"},
    {"text":"82 probe at third (56)",                                                                                                                                 "time":"8:08"},
    {"text":"83 1 more gateway and send 3rd observer to scout",                                                                                                       "time":"8:13"},
    {"text":"83 2 pylons at third expo to make wallin and send a probe to take a forth",                                                                              "time":"8:18"},
    {"text":"83 probe at main (57)",                                                                                                                                  "time":"8:24"},
    {"text":"84 probe at natural (58)",                                                                                                                               "time":"8:24"},
    {"text":"85 probe at third (59)",                                                                                                                                 "time":"8:24"},
    {"text":"86 take a fourth expo (only because terran takes a third, if he is going factories, add more gateways)",                                                 "time":"8:33"},
    {"text":"86 1st arbiter",                                                                                                                                         "time":"8:35"},
    {"text":"90 probe at third (60) and research zealot speed and pylon at fourth expo for cannons",                                                                  "time":"8:45"},
    {"text":"91 scout with observer his main",                                                                                                                        "time":"8:50"},
    {"text":"91 probe at main (61)",                                                                                                                                  "time":"8:53"},
    {"text":"92 probe at natural (62)",                                                                                                                               "time":"8:53"},
    {"text":"93 probe at third (63)",                                                                                                                                 "time":"8:53"},
    {"text":"94 2 pylons at gateways",                                                                                                                                "time":"8:56"},
    {"text":"94 make 6 dragoons",                                                                                                                                     "time":"9:08"},
    {"text":"106 2 pylons at fourth expo to make wallin",                                                                                                             "time":"9:12"},
    {"text":"106 probe at main (64)",                                                                                                                                 "time":"9:14"},
    {"text":"107 probe at natural (65)",                                                                                                                              "time":"9:14"},
    {"text":"108 probe at third (66)",                                                                                                                                "time":"9:14"},
    {"text":"109 from here only make units, no more probes",                                                                                                          "time":"9:25"},
    {"text":"109 move back with army, make 2-3 observers, send 6 probes from first 2 bases to fourth expo and make 1 cannon at each base",                            "time":"9:34"},
    {"text":"110 make 6 zealots",                                                                                                                                     "time":"9:41"},
    {"text":"122 4 more gateways",                                                                                                                                    "time":"9:45"},
    {"text":"123 make 6 zealots even 1-3 shuttles",                                                                                                                   "time":"10:05"},
    {"text":"135 research stasis field or recall and make 2nd arbiter",                                                                                               "time":"10:25"},
    {"text":"139 send a probe to take a 5th expo and make a pylon",                                                                                                   "time":"10:32"},
    {"text":"140 take a 5th expo and make 4 pylons for cannons and gateways",                                                                                         "time":"10:45"},
    {"text":"140 +2 ground weapons",                                                                                                                                  "time":"10:49"},
    {"text":"142 make 10 zealots",                                                                                                                                    "time":"10:54"},
    {"text":"162 make 1-2 more cannons at each expo",                                                                                                                 "time":"11:13"},
    {"text":"164 make 10 zealots and send 6 probes from first 2 bases to 5th expo",                                                                                   "time":"11:30"},
    {"text":"184 make zealots",                                                                                                                                       "time":"11:54"},
    {"text":"200 you are maxed out and can attack anywhere, keep making units and arbiters",                                                                          "time":"12:00"},
    {"text":"200 research 2nd arbiter spell",                                                                                                                         "time":"12:05"},
    {"text":"200 don't lose dragoons in engages, only zealots and keep trading them and take 1-2 more expos",                                                         "time":"12:10"},
    {"text":"200 research storm and take 2 more gases",                                                                                                               "time":"12:15"},
    {"text":"200 make 4-6 more gateways",                                                                                                                             "time":"12:20"},
    {"text":"200 +3 ground weapons and research arbiter energy and make 4-6 cannons at the new expos and send probes there",                                          "time":"13:54"},
    {"text":"200 take 1-2 more forges and another expo",                                                                                                              "time":"14:05"},
    {"text":"200 scout his main and if no mines recall there if he is moving out",                                                                                    "time":"14:10"},
    {"text":"200 have 16-24 dragoons in army, 3-4 arbiters, 3-4 high templars when engaging and try to trade only zealots",                                           "time":"14:15"},
    {"text":"200 keep an arbiter in position to recall and take as many expos as you can with cannons defending them",                                                "time":"14:20"},
    {"text":"200 get all upgrades",                                                                                                                                   "time":"14:25"},
    {"text":"200 get 8-10 more gateways at another main",                                                                                                             "time":"14:30"},
    {"text":"200 END OF BUILD ORDER",                                                                                                        			                    "time":"14:40"}
  ]
}
