11 Nexus (Beast) (vs. Zerg)

4 0:01 probe (5)
5 0:16 probe (6)
6 0:29 probe (7)
7 0:38 75% send a probe to natural
7 0:42 probe (8)
8 0:50 pylon and don't pylon scout
8 0:57 probe (9)
9 1:12 probe (10)
10 1:25 probe (11)
11 1:47 send the 11th probe (1:38) to make nexus at natural and don't scout
11 1:59 forge then scout cross-map 
11 2:03 probe (12)
12 2:15 probe (13)
13 2:26 75% send a probe to natural
13 2:28 probe (14)
14 2:37 1st cannon at natural 
14 2:40 1st gateway (scout the 3rd)
14 2:43 probe (15)
15 2:53 gas and send 4 probes to natural minerals
15 2:56 probe (16) (split the 5 probes at natural)
16 3:06 probe at natural (17)
17 3:10 probe at main (18)
18 3:20 probe at natural (19)
19 3:22 probe at main (20) and send 3 probes to gas with this one
20 3:25 core at natural (17)
20 3:34 probe at natural (21)
21 3:36 probe at main (22) 
22 3:39 pylon at main
22 3:46 probe at natural (23)
23 3:47 1st zealot or 2nd cannon if ling all-in
25 3:51 probe at main (24) 
26 4:01 probe at natural (25)
27 4:05 probe at main (26) and make stargate with this one
28 4:10 gas at natural
28 4:14 probe at natural (27)
29 4:17 probe at main (28) 
30 4:20 +1 ground weapons
30 4:25 2nd zealot
32 4:31 pylon at natural
32 4:35 probe at natural (29)
33 4:36 probe at main (30) 
34 4:39 +1 air weapons and send 3 probes to natural gas
34 4:52 probe at natural (31)
35 4:53 probe at main (32) 
36 4:54 1st corsair
38 4:58 pylon at natural
38 5:05 3rd zealot
40 5:05 probe at natural (33)
41 5:05 probe at main (34) 
41 5:08 citadel at main (scouting probe dies)
41 5:14 2nd gateway at natural
41 5:20 probe at natural (34)
42 5:20 probe at main (35) 
43 5:21 2nd corsair and send 1st corsair to scout and maybe kill an overlord there
45 5:29 pylon at main
45 5:33 4th zealot
47 5:38 probe at natural (36)
48 5:38 probe at main (37) 
49 5:49 3rd corsair and send 2nd corsair to other area of map to kill overlord (stop making probes for 2 rounds and keep making zealots and corsairs)
49 5:51 research zealot speed
51 5:52 pylon at main
51 5:57 5th zealot at 2nd gateway
53 6:00 6th zealot at 1st gateway
55 6:05 pylon at natural 
57 6:16 4th corsair
57 6:21 probe at natural (38) (resume probe production)
58 6:21 probe at main (39) 
59 6:26 templar archives at main 
59 6:28 cannon near stargate
59 6:29 7th zealot at 1st gateway
61 6:32 8th zealot at 2nd gateway (rally corsairs at natural)
65 6:44 pylon at main (block a probe with this one)
65 6:47 5th corsair
67 6:55 9th zealot at 1st gateway
69 6:58 10th zealot at 2nd gateway
71 6:59 pylon at natural
71 6:59 probe at main (40) 
72 7:01 probe at natural (41)
73 7:05 2nd cannon at natural
73 7:13 research storm and move out with 10 +1 zealots 
73 7:21 1st high templar at 1st gateway
75 7:23 2nd high templar at 2nd gateway
77 7:26 probe at natural (42)
78 7:26 probe at main (43) and move out with 5 +1 corsairs
79 7:32 +2 ground weapons
79 7:36 pylon at main
79 7:53 probe at natural (44)
80 7:53 probe at main (45)
81 7:54 3rd high templar at 1st gateway
83 7:55 4th high templar at 2nd gateway
85 7:57 3rd gateway at main
85 7:59 4th gateway at main
85 8:03 6th corsair and attack 3rd expo with army if natural is defended well, after killing overlords at 3rd expo go to main and kill those overlords
xx 8:31 probe at natural (46)
xx 8:31 probe at main (47)
xx 8:32 5th gateway at main
xx 8:33 6th gateway at main
xx 8:34 zealot at 1st gateway
xx 8:34 zealot at 2nd gateway
xx 8:41 3rd cannon at natural
xx 8:44 probe at natural (48)
xx 8:44 probe at main (49)
xx 8:47 robotics and research goon range
xx 8:49 4 dragoons at first 4 gateways
xx 8:59 pylon at main
xx 9:16 2 dragoons at last 2 gateways
xx 9:16 probe at natural (50)
xx 9:16 probe at main (51)
xx 9:29 pylon at main (keep rebuilding corsairs if you lose them until you have 5) and keep making dragoons and zealots if low on gas
xx 9:42 observatory
xx 10:06 probe at natural (52)
xx 10:06 probe at main (53)
xx 10:07 pylon at natural
xx 10:18 take 3rd expo build 2 pylons there and move out with whole army to defend it
xx 10:30 build 2 observers
xx 10:32 keep making dragoons and zealots if low on gas
xx 10:36 pylon at natural
xx 10:45 +3 ground weapons and move a bit out with ground army also with corsairs scout for 4th expo
xx 11:00 pylon at main near the 4 gateways
xx 11:01 cannon at 3rd expo
xx 11:16 2 more cannons at 3rd expo
xx 11:17 probe at natural (54)
xx 11:17 probe at main (55)
xx 11:18 send 7 probes from natural and 9 probes from main to 3rd expo
xx 11:26 4 more gateways at main
xx 11:41 keep making dragoons, 1 high templar and zealots if low on gas
xx 12:22 probe at 3rd (56)
xx 12:23 pylon at 3rd
xx 12:28 keep making dragoons, 1 high templar and zealots if low on gas and attack with whole army to take a 4th near opponent
xx 12:30 research templar energy
xx 12:50 take a 4th expo near the whole army and build a pylon next to it
xx 12:56 keep making dragoons, 1 high templar and zealots if low on gas and attack with whole army the natural
xx 13:20 keep making dragoons, 1 high templar and zealots if low on gas
xx 13:22 2 more pylons at 4th
xx 13:40 keep making dragoons, 1 high templar and zealots if low on gas
xx 13:56 attack with rallied army the 4th
xx 14:12 2 cannons at 4th
xx 14:14 keep making dragoons, 1 high templar and zealots if low on gas
xx 14:30 keep making dragoons, 1 high templar and zealots if low on gas













 