{
  "Title": "1 Gate Robo (Rain) (vs. Protoss)",
  "Link": "https://www.youtube.com/watch?v=MSSHcPzcn5o",
  "secondsDelayed": -5,
  "buildSteps":[
    {"text":"4 probe (5) and split probes",                                                                                                                           "time":"0:05"},
    {"text":"5 probe (6)",                                                                                                                                            "time":"0:16"},
    {"text":"6 probe (7)",                                                                                                                                            "time":"0:29"},
    {"text":"7 probe (8)",                                                                                                                                            "time":"0:42"},
    {"text":"8 pylon",                                                                                                                                                "time":"0:50"},
    {"text":"8 probe (9)",                                                                                                                                            "time":"0:57"},
    {"text":"9 probe (10)",                                                                                                                                           "time":"1:12"},
    {"text":"10 gateway",                                                                                                                                             "time":"1:14"},
    {"text":"10 probe (11)",                                                                                                                                          "time":"1:22"},
    {"text":"11 probe (12)",                                                                                                                                          "time":"1:33"},
    {"text":"12 gas",                                                                                                                                                 "time":"1:34"},
    {"text":"12 probe (13)",                                                                                                                                          "time":"1:44"},
    {"text":"13 core and send probe to scout vertically then horizontically on circuit breakers",                                                                     "time":"1:58"},
    {"text":"13 probe (14) and send 3 probes to gas",                                                                                                                 "time":"2:00"},
    {"text":"14 zealot",                                                                                                                                              "time":"2:09"},
    {"text":"16 pylon (block outer minerals with this one or near nexus to prevent manner pylon)",                                                                    "time":"2:19"},
    {"text":"16 probe (15)",                                                                                                                                          "time":"2:24"},
    {"text":"17 probe (16)",                                                                                                                                          "time":"2:39"},
    {"text":"18 1st dragoon",                                                                                                                                         "time":"2:42"},
    {"text":"20 probe (17)",                                                                                                                                          "time":"2:54"},
    {"text":"21 research goon range",                                                                                                                                 "time":"2:57"},
    {"text":"21 probe (18)",                                                                                                                                          "time":"3:07"},
    {"text":"22 pylon at entrance for robotics",                                                                                                                      "time":"3:12"},
    {"text":"22 2nd dragoon",                                                                                                                                         "time":"3:19"},
    {"text":"24 probe (19), if last scout, don't send the probe to scout anymore, send the 1st dragoon to scout",                                                     "time":"3:23"},
    {"text":"25 probe (20)",                                                                                                                                          "time":"3:35"},
    {"text":"26 robotics",                                                                                                                                            "time":"3:43"},
    {"text":"26 probe (21)",                                                                                                                                          "time":"3:50"},
    {"text":"27 3rd dragoon",                                                                                                                                         "time":"3:55"},
    {"text":"29 probe (22) and check for enemy pylon placement to guess his tech (scouting probe dies)",                                                              "time":"4:03"},
    {"text":"29 pylon in the corner for tech",                                                                                                                        "time":"4:07"},
    {"text":"29 probe (23)",                                                                                                                                          "time":"4:15"},
    {"text":"30 4th dragoon",                                                                                                                                         "time":"4:25"},
    {"text":"32 probe (24)",                                                                                                                                          "time":"4:29"},
    {"text":"33 observatory",                                                                                                                                         "time":"4:36"},
    {"text":"33 support bay",                                                                                                                                         "time":"4:38"},
    {"text":"33 probe (25)",                                                                                                                                          "time":"4:41"},
    {"text":"34 pylon to spot drops",                                                                                                                                 "time":"4:45"},
    {"text":"34 probe (26)",                                                                                                                                          "time":"4:53"},
    {"text":"35 1st observer",                                                                                                                                        "time":"4:58"},
    {"text":"36 5th dragoon",                                                                                                                                         "time":"5:03"},
    {"text":"38 probe (27)",                                                                                                                                          "time":"5:07"},
    {"text":"39 probe (28)",                                                                                                                                          "time":"5:19"},
    {"text":"40 1st reaver",                                                                                                                                          "time":"5:24"},
    {"text":"44 6th dragoon and send observer to scout enemy natural if you are sure he is going robotics also, if not, then keep it with your army",                 "time":"5:33"},
    {"text":"44 send a probe to nat",                                                                                                                                 "time":"5:36"},
    {"text":"46 nexus",                                                                                                                                               "time":"5:47"},
    {"text":"46 pylon at natural and wallin using your army in case of enemy DT build",                                                                               "time":"5:52"},
    {"text":"46 probe (29)",                                                                                                                                          "time":"5:53"},
    {"text":"47 probe (30)",                                                                                                                                          "time":"6:08"},
    {"text":"48 7th dragoon",                                                                                                                                         "time":"6:14"},
    {"text":"50 2nd reaver (probe and shuttle were cancelled because enemy has no natural yet and he is attacking with shuttle reaver)",                              "time":"6:17"},
    {"text":"54 probe (31)",                                                                                                                                          "time":"6:21"},
    {"text":"55 shield battery and another pylon at natural because enemy is attacking",                                                                              "time":"6:25"},
    {"text":"55 probe (32) and keep observer on enemy shuttle and/or army",                                                                                           "time":"6:34"},
    {"text":"56 probe (33) and spread your army",                                                                                                                     "time":"6:47"},
    {"text":"57 8th dragoon",                                                                                                                                         "time":"6:50"},
    {"text":"59 probe at main (34)",                                                                                                                                  "time":"6:59"},
    {"text":"60 3rd reaver (only because enemy is attacking without expanding and if you are not confident on your micro) and send 12 probes to natural minerals",    "time":"7:04"},
    {"text":"64 probe at natural (35)",                                                                                                                               "time":"7:06"},
    {"text":"65 probe at main (36)",                                                                                                                                  "time":"7:13"},
    {"text":"66 2 pylons at main near gateway",                                                                                                                       "time":"7:17"},
    {"text":"66 probe at natural (37)",                                                                                                                               "time":"7:21"},
    {"text":"67 probe at main (38)",                                                                                                                                  "time":"7:24"},
    {"text":"68 9th dragoon",                                                                                                                                         "time":"7:34"},
    {"text":"70 probe at natural (39)",                                                                                                                               "time":"7:37"},
    {"text":"71 probe at main (40)",                                                                                                                                  "time":"7:38"},
    {"text":"72 shuttle",                                                                                                                                             "time":"7:48"},
    {"text":"74 probe at main (41)",                                                                                                                                  "time":"7:50"},
    {"text":"75 probe at natural (42)",                                                                                                                               "time":"7:51"},
    {"text":"75 2nd gateway",                                                                                                                                         "time":"7:59"},
    {"text":"75 10th dragoon and add 2 more gateways",                                                                                                                "time":"8:10"},
    {"text":"77 probe at main (42)",                                                                                                                                  "time":"8:15"},
    {"text":"78 probe at natural (43)",                                                                                                                               "time":"8:16"},
    {"text":"79 pylon at natural for cannons",                                                                                                                        "time":"8:18"},
    {"text":"79 probe at main (44)",                                                                                                                                  "time":"8:24"},
    {"text":"80 probe at natural (45) (observer dies)",                                                                                                               "time":"8:25"},
    {"text":"80 2nd observer",                                                                                                                                        "time":"8:35"},
    {"text":"81 probe at main (46)",                                                                                                                                  "time":"8:39"},
    {"text":"82 probe at natural (47)",                                                                                                                               "time":"8:40"},
    {"text":"83 dragoon and send the shuttle with 1 reaver to harass",                                                                                                "time":"8:41"},
    {"text":"85 make 3 dragoons from the 3 gateways",                                                                                                                 "time":"8:50"},
    {"text":"91 probe at main (48)",                                                                                                                                  "time":"8:52"},
    {"text":"92 probe at natural (49)",                                                                                                                               "time":"8:53"},
    {"text":"93 make 2 pylons at gateways and send 2 dragoons at main to defend vs reaver harass",                                                                    "time":"8:54"},
    {"text":"93 3rd observer",                                                                                                                                        "time":"8:60"},
    {"text":"94 probe at main (50)",                                                                                                                                  "time":"9:04"},
    {"text":"95 probe at natural (51)",                                                                                                                               "time":"9:05"},
    {"text":"96 pylon at natural for cannons",                                                                                                                        "time":"9:06"},
    {"text":"96 gas at natural",                                                                                                                                      "time":"9:08"},
    {"text":"96 citadel",                                                                                                                                             "time":"9:10"},
    {"text":"96 forge",                                                                                                                                               "time":"9:11"},
    {"text":"96 probe at main (52)",                                                                                                                                  "time":"9:19"},
    {"text":"97 probe at natural (53)",                                                                                                                               "time":"9:19"},
    {"text":"98 make 4 dragoons and send 3 to defend natural against reaver drop",                                                                                    "time":"9:30"},
    {"text":"106 probe at main (54)",                                                                                                                                 "time":"9:38"},
    {"text":"107 probe at natural (55) and send 3 probes to natural gas",                                                                                             "time":"9:39"},
    {"text":"108 4th observer and send 1 observer behind your natural",                                                                                               "time":"9:44"},
    {"text":"109 2 more gateways",                                                                                                                                    "time":"9:49"},
    {"text":"109 make 4 dragoons and 2 pylons",                                                                                                                       "time":"10:05"},
    {"text":"117 shuttle",                                                                                                                                            "time":"10:15"},
    {"text":"119 make 4 dragoons",                                                                                                                                    "time":"10:22"},
    {"text":"127 2 more gateways",                                                                                                                                    "time":"10:23"},
    {"text":"127 probe at main (56)",                                                                                                                                 "time":"10:24"},
    {"text":"128 probe at natural (57)",                                                                                                                              "time":"10:25"},
    {"text":"129 +1 ground weapons",                                                                                                                                  "time":"10:30"},
    {"text":"129 templar archives and 2 pylons and move out with army",                                                                                               "time":"10:32"},
    {"text":"129 probe at main (58)",                                                                                                                                 "time":"10:39"},
    {"text":"130 probe at natural (59)",                                                                                                                              "time":"10:40"},
    {"text":"131 research zealot speed",                                                                                                                              "time":"10:48"},
    {"text":"131 make 5 zealots (only make dragoons to match enemy dragoons)",                                                                                        "time":"10:57"},
    {"text":"141 zealot and 7th gateway and send a probe to take a third",                                                                                            "time":"11:10"},
    {"text":"143 make 1-2 cannons at main and 2-4 at natural in case of enemy DT",                                                                                    "time":"11:20"},
    {"text":"143 take a third expo and attack with army",                                                                                                             "time":"11:28"},
    {"text":"143 make high templars and zealots if low on gas",                                                                                                       "time":"11:33"},
    {"text":"157 3 pylons at third",                                                                                                                                  "time":"11:47"},
    {"text":"xxx for noobs get archons not templars, get up to 10 gateways, wait for speed upgrade and spend minerals on zealots and templars",                       "time":"12:14"},
    {"text":"xxx 4-6 cannons and pylons at third",                                                                                                                    "time":"12:30"},
    {"text":"xxx END OF BUILD ORDER",                                                                                                        			                    "time":"12:40"}
  ]
}
