{
  "Title": "1 Base Reaver (NonY) (vs. Terran)",
  "Link": "https://www.youtube.com/watch?v=mglr_FTsCdE",
  "secondsDelayed": -5,
  "buildSteps":[
    {"text":"4 probe (5) and split probes",                                                                                                                           "time":"0:05"},
    {"text":"5 probe (6)",                                                                                                                                            "time":"0:16"},
    {"text":"6 probe (7)",                                                                                                                                            "time":"0:29"},
    {"text":"7 probe (8)",                                                                                                                                            "time":"0:42"},
    {"text":"8 pylon",                                                                                                                                                "time":"0:50"},
    {"text":"8 probe (9)",                                                                                                                                            "time":"0:57"},
    {"text":"9 probe (10)",                                                                                                                                           "time":"1:12"},
    {"text":"10 gateway",                                                                                                                                             "time":"1:18"},
    {"text":"10 probe (11)",                                                                                                                                          "time":"1:22"},
    {"text":"11 probe (12)",                                                                                                                                          "time":"1:33"},
    {"text":"12 gas",                                                                                                                                                 "time":"1:39"},
    {"text":"12 probe (13)",                                                                                                                                          "time":"1:49"},
    {"text":"13 core and send probe to scout",                                                                   						                                          "time":"2:00"},
    {"text":"13 probe (14)",                                                                                                                 			                    "time":"2:03"},
    {"text":"14 send 3 probes to gas",                                                                                                                                "time":"2:05"},
    {"text":"14 pylon",                                                                                                                 			                        "time":"2:14"},
    {"text":"15 probe (15)",                                                                                                                                          "time":"2:18"},
    {"text":"15 probe (16)",                                                                                                                                          "time":"2:32"},
    {"text":"16 1st dragoon",                                                                                                                                         "time":"2:40"},
    {"text":"18 probe (17)",                                                                                                                                          "time":"2:44"},
    {"text":"19 +1 air weapons",                                                                                                                                      "time":"2:52"},
    {"text":"19 probe (18)",                                                                                                                                          "time":"2:59"},
    {"text":"20 probe (19)",                                                                                                                                          "time":"3:10"},
    {"text":"21 cancel +1 air weapons and build robotics (only if enemy scv is not in your main)",                                                                    "time":"3:12"},
    {"text":"21 2nd dragoon",                                                                                                                                         "time":"3:15"},
    {"text":"23 probe (20)",                                                                                                                                          "time":"3:23"},
    {"text":"24 pylon",                                                                                                                                               "time":"3:26"},
    {"text":"24 probe (21)",                                                                                                                                          "time":"3:36"},
    {"text":"25 probe (22)",                                                                                                                                          "time":"3:48"},
    {"text":"26 3rd dragoon",                                                                                                                                         "time":"3:49"},
    {"text":"28 probe (23)",                                                                                                                                          "time":"4:01"},
    {"text":"29 shuttle",                                                                                                                                             "time":"4:06"},
    {"text":"31 support bay",                                                                                                                                         "time":"4:11"},
    {"text":"31 probe (24)",                                                                                                                                          "time":"4:15"},
    {"text":"32 pylon",                                                                                                                                               "time":"4:20"},
    {"text":"32 probe (25)",                                                                                                                                          "time":"4:26"},
    {"text":"33 pylon",                                                                                                                                               "time":"4:30"},
    {"text":"33 probe (26)",                                                                                                                                          "time":"4:42"},
    {"text":"34 reaver",                                                                                                                                              "time":"4:45"},
    {"text":"38 1st zealot",                                                                                                                                          "time":"4:51"},
    {"text":"40 probe (27)",                                                                                                                                          "time":"4:54"},
    {"text":"41 observatory",                                                                                                                                         "time":"4:57"},
    {"text":"41 probe (28)",                                                                                                                                          "time":"5:07"},
    {"text":"42 research goon range",                                                                                                                                 "time":"5:10"},
    {"text":"42 2nd zealot",                                                                                                                                          "time":"5:16"},
    {"text":"44 probe (29)",                                                                                                                                          "time":"5:19"},
    {"text":"45 pylon",                                                                                                                                               "time":"5:24"},
    {"text":"45 1st observer",                                                                                                                                        "time":"5:30"},
    {"text":"46 probe (30)",                                                                                                                                          "time":"5:33"},
    {"text":"47 4th dragoon and move out with loaded shuttle",                                                                                                        "time":"5:42"},
    {"text":"49 probe (31)",                                                                                                                                          "time":"5:48"},
    {"text":"50 2nd gateway or save minerals for nexus if he isn't attacking",                                                                                        "time":"5:50"},
    {"text":"49 probe (31)",                                                                                                                                          "time":"6:01"},
    {"text":"50 attack with 3 goons the front and harass with shuttle the main focusing tanks",                                                                       "time":"6:05"},
    {"text":"50 drop zealots first then reaver and keep loading and unloading it (1 zealot dies)",                                                                    "time":"6:10"},
    {"text":"48 make 2 goons",     														                                                                                                        "time":"6:13"},
    {"text":"52 nexus (1 goon dies)",                                                                                                                                 "time":"6:22"},
    {"text":"END OF BUILD ORDER",                                                                                                                                     "time":"6:40"}
  ]
}
