{
  "Title": "5 Gate Goons (Best) (vs. Zerg)",
  "Link": "https://www.youtube.com/watch?app=desktop&v=Shmwg_Glwuk&feature=youtu.be",
  "secondsDelayed": -5,
  "buildSteps":[
    {"text":"4 probe (5) and split probes",                                                                                       "time":"0:05"},
    {"text":"5 probe (6)",                                                                                                        "time":"0:16"},
    {"text":"6 probe (7)",                                                                                                        "time":"0:29"},
    {"text":"7 75% send a probe to natural",                                                                                      "time":"0:38"},
    {"text":"7 probe (8)",                                                                                                        "time":"0:42"},
    {"text":"8 pylon and send it to scout vertically on circuit breakers",                                                        "time":"0:50"},
    {"text":"8 probe (9)",                                                                                                        "time":"0:57"},
    {"text":"9 probe (10)",                                                                                                       "time":"1:12"},
    {"text":"10 probe (11) and send the 10th probe to natural and 1st scout horizontically if you didn't find enemy",             "time":"1:25"},
    {"text":"11 forge and send it to scout horizontically on circuit breakers if 1st scout didn't find enemy",                    "time":"1:36"},
    {"text":"11 probe (12)",                                                                                                      "time":"1:37"},
    {"text":"12 probe (13)",                                                                                                      "time":"1:48"},
    {"text":"13 if you find enemy in cross position send a probe to natural and recall 2nd scout",                                "time":"2:02"},
    {"text":"13 nexus",                                                                                                           "time":"2:13"},
    {"text":"13 1st cannon at natural",                                                                                           "time":"2:26"},
    {"text":"13 probe (14)",                                                                                                      "time":"2:31"},
    {"text":"14 probe (15)",                                                                                                      "time":"2:44"},
    {"text":"15 gateway at natural to complete wall",                                                                             "time":"2:47"},
    {"text":"15 probe (16)",                                                                                                      "time":"2:56"},
    {"text":"16 pylon at main",                                                                                                   "time":"3:00"},
    {"text":"16 probe (17) and gas",                                                                                              "time":"3:10"},
    {"text":"17 probe (18) and send 4 probes to natural minerals",                                                                "time":"3:22"},
    {"text":"18 core at main",                                                                                                    "time":"3:36"},
    {"text":"18 probe at main (19)",                                                                                              "time":"3:35"},
    {"text":"19 probe at natural (20) and send 3 probes to gas",                                                                  "time":"3:39"},
    {"text":"20 1st zealot",                                                                                                      "time":"3:46"},
    {"text":"22 probe at main and send it to natural minerals (21)",                                                      	      "time":"3:49"},
    {"text":"23 probe at natural (22)",                                                              				                      "time":"3:51"},
    {"text":"24 probe at main and send it to natural minerals (23)",                           	                                  "time":"4:04"},
    {"text":"25 probe at natural (24)",                    			                                                                  "time":"4:05"},
    {"text":"26 2nd zealot",                                                                                                      "time":"4:10"},
    {"text":"28 probe at main (25)",                                                                                              "time":"4:18"},
    {"text":"29 probe at natural (26)",                                                                                           "time":"4:18"},
    {"text":"30 research goon range",                                                                                             "time":"4:19"},
    {"text":"30 probe at main (27)",                                                                                              "time":"4:30"},
    {"text":"31 probe at natural (28)",                                                                                           "time":"4:30"},
    {"text":"32 pylon at main for gateways",                                                                                      "time":"4:31"},
    {"text":"32 +1 ground weapons",                                                                                               "time":"4:36"},
    {"text":"32 3rd zealot (scouting probe dies)",                                                                                "time":"4:37"},
    {"text":"33 probe at main (29)",                                                                                              "time":"4:56"},
    {"text":"34 probe at natural (30)",                                                                                           "time":"4:56"},
    {"text":"35 make 4 gateways",                                                                                                 "time":"4:59"},
    {"text":"35 1st dragoon",                                                                                                     "time":"5:12"},
    {"text":"37 pylon at main",                                                                                                   "time":"5:19"},
    {"text":"37 2nd cannon and another pylon at natural",                                                                         "time":"5:24"},
    {"text":"37 make 5 more dragoons",                                                                                            "time":"5:49"},
    {"text":"47 3rd cannon at natural",                       			                                                              "time":"6:00"},
    {"text":"47 keep making dragoon out of all the gateways",                                                                     "time":"6:24"},
    {"text":"57 pylon at natural",                      	                                                                        "time":"6:31"},
    {"text":"57 2 pylons at main",                                                                                                "time":"6:38"},
    {"text":"57 gas at natural",                                                                                                  "time":"6:43"},
    {"text":"57 when moving out keep poking enemy units and micro your dragoons",                                                 "time":"7:02"},
    {"text":"57 make 4 more dragoons and 1 zealot",                                                                               "time":"7:05"},
    {"text":"67 2 pylons and send 3 probes to natural gas",                             	                                        "time":"7:12"},
    {"text":"67 citadel",                                                                        			                            "time":"7:31"}
  ]
}
